ejemplo/Tarea2/Reg32/RegDesp.v
module RegDesp(clk, enb, dir, sIn, modo, D, Q, sOut) ;

  input clk, //clock
        enb, //enabler
        dir, //dir
        sIn; //entrada de dato
  input [1:0] modo; //modo
  input [3:0] D; //entrada de datos

  output reg [3:0] Q;//salida de estado
  output reg sOut; //salida de dato


	always @ (posedge clk) begin
    if(enb) begin//de esta forma solo se ejecutara cuando el enabler este en 1
    //luego se chequea si se quiere a la derecha (dir=1) o a la Izquierda (dir=0)
      if (dir) begin //Rotar Derecha: dir=1
        if (modo==2'b00)begin//se chequea si se quiere una rotacion a la derecha: modo=00
          Q <= {sIn, Q[3:1]};
          sOut <= Q[0];
        end //end modo=00

        else if (modo==2'b01) begin //Rotar Derecha Circular: modo=01
          Q <= {Q[0],Q[3:1]};
          sOut <= 0;//ya que es circular, no hay dato que salga... por ende se saca un 0 por especificacion
        end //modo=01
      end//end dir=1
      else begin //Rotar Izquierda dir=0
        if (modo==2'b00)begin//se chequea si se quiere una rotacion a la izquierda: modo=00
          Q <= {Q[2:0], sIn};
          sOut <= Q[3];
        end //modo=00
        else if (modo==2'b01) begin //Rotar Izquierda Circular: modo=01
          Q <= {Q[2:0],Q[3]};
          sOut <= 0;
        end //modo 01
      end//end dir=0

      if(modo==2'b10) begin//carga Paralelo: Modo=10 & dir=x; esto porque se ignora la direccion
        Q <= D[3:0];
        sOut <= 0;
      end// end carga Paralela

    end//end enb
  end//end always
endmodule

ejemplo/Tarea2/Reg32/RegDesp32.v


module RegDesp32(clk, enb, dir, sIn, modo, D, Q, sOut) ;

  input clk, //clock
        enb, //enabler
        dir, //dir
        sIn; //entrada de dato
  input [1:0] modo; //modo
  input [31:0] D; //entrada de datos

  input [3:0] D1, D2, D3, D4, D5, D6, D7, D8;

  output wire [31:0] Q;//salida de estado
  output wire sOut; //salida de dato
  output wire [3:0] Q1;
  output wire [3:0] Q2;
  output wire [3:0] Q3;
  output wire [3:0] Q4;
  output wire [3:0] Q5;
  output wire [3:0] Q6;
  output wire [3:0] Q7;
  output wire [3:0] Q8;

  output wire sOut1;
  output wire sOut2;
  output wire sOut3;
  output wire sOut4;
  output wire sOut5;
  output wire sOut6;
  output wire sOut7;
  output wire sOut8;

  RegDesp registro1(clk,enb,dir,sIn,modo,D1,Q1,sOut1);
  RegDesp registro2(clk,enb,dir,sOut1,modo,D2,Q2,sOut2);
  RegDesp registro3(clk,enb,dir,sOut2,modo,D3,Q3,sOut3);
  RegDesp registro4(clk,enb,dir,sOut3,modo,D4,Q4,sOut4);
  RegDesp registro5(clk,enb,dir,sOut4,modo,D5,Q5,sOut5);
  RegDesp registro6(clk,enb,dir,sOut5,modo,D6,Q6,sOut6);
  RegDesp registro7(clk,enb,dir,sOut6,modo,D7,Q7,sOut7);
  RegDesp registro8(clk,enb,dir,sOut7,modo,D8,Q8,sOut);

/*
  assign D1 = D[31:28];
  assign D2 = D[27:24];
  assign D3 = D[23:20];
  assign D4 = D[19:16];
  assign D5 = D[15:12];
  assign D6 = D[11:8];
  assign D7 = D[7:4];
  assign D8 = D[3:0];
*/
  assign D8 = D[31:28];
  assign D7 = D[27:24];
  assign D6 = D[23:20];
  assign D5 = D[19:16];
  assign D4 = D[15:12];
  assign D3 = D[11:8];
  assign D2 = D[7:4];
  assign D1 = D[3:0];

  //assign Q = {Q1[3:0],Q2[3:0],Q3[3:0],Q4[3:0],Q5[3:0],Q6[3:0],Q7[3:0],Q8[3:0]};
  assign Q = {Q8[3:0],Q7[3:0],Q6[3:0],Q5[3:0],Q4[3:0],Q3[3:0],Q2[3:0],Q1[3:0]};
endmodule

ejemplo/Tarea2/Reg32/tester32.v
module tester32(clk,enb,dir,sIn,modo,D);
  output reg clk,enb,dir,sIn;
  output reg [1:0] modo;
  output reg [31:0] D;

  always #2 clk = !clk;

  initial begin

    clk <=0;
    enb <= 1;
    dir <= 0;
    sIn <= 1;
    modo <= 2'b00;

    $display("Prueba 1; Rotacion a la Izquierda");
      modo <= 2'b00;
      dir <= 1'b0;
      D <= 32'b11110001000100010001000100010001;
      #152;

    $display("Prueba 5; Carga en Paralelo");
      D <= 32'b11110001000100010001000100010001;
      modo <= 2'b10;
      enb <= 1'b1;
      #4;

    $display("Prueba 2; Rotacion a la Derecha");
      modo <= 2'b00;
    	dir <= 1'b1;
      #152;

    $display("Prueba 5; Carga en Paralelo");
      D <= 32'b11110001000100010001000100010001;
      modo <= 2'b10;
      enb <= 1'b1;
      #4;

    $display("Prueba 3; Rotacion Circular a la Izquierda");
      modo <= 2'b01;
      dir <= 1'b0;
      #152;

    $display("Prueba 5; Carga en Paralelo");
      D <= 32'b11110001000100010001000100010001;
      modo <= 2'b10;
      enb <= 1'b1;
      #4;


    $display("Prueba 4; Rotacion Circular a la Derecha");
      modo <= 2'b01;
    	dir <= 1'b1;
    	#152;


    $finish;
      end
endmodule

ejemplo/Tarea2/Reg32/testbench2.v
module testbench2();
  wire [31:0] D;
  output wire [31:0] Q;
  wire [1:0] modo;
  tester32 prueba(clk,enb,dir,sIn,modo,D);
  RegDesp32 registro(clk,enb,dir,sIn,modo,D,Q,sOut);
  initial begin
    $dumpfile("resultado.vcd");
    $dumpvars;
    $display ("time\t clk  enb  dir  sIn  modo    D       Q    sOut");
    $monitor ("%g\t    %b  %b    %b    %b    %b    %b    %b   %b",
    $time, clk, enb, dir, sIn, modo, D, Q, sOut);
  end
endmodule

ejemplo/Tarea2/Reg32/resultado.vcd
$date
	Fri May  8 12:22:26 2020
$end
$version
	Icarus Verilog
$end
$timescale
	1s
$end
$scope module testbench2 $end
$var wire 1 ! sOut $end
$var wire 1 " sIn $end
$var wire 2 # modo [1:0] $end
$var wire 1 $ enb $end
$var wire 1 % dir $end
$var wire 1 & clk $end
$var wire 32 ' Q [31:0] $end
$var wire 32 ( D [31:0] $end
$scope module prueba $end
$var reg 32 ) D [31:0] $end
$var reg 1 & clk $end
$var reg 1 % dir $end
$var reg 1 $ enb $end
$var reg 2 * modo [1:0] $end
$var reg 1 " sIn $end
$upscope $end
$scope module registro $end
$var wire 32 + D [31:0] $end
$var wire 1 & clk $end
$var wire 1 % dir $end
$var wire 1 $ enb $end
$var wire 2 , modo [1:0] $end
$var wire 1 " sIn $end
$var wire 1 - sOut8 $end
$var wire 1 . sOut7 $end
$var wire 1 / sOut6 $end
$var wire 1 0 sOut5 $end
$var wire 1 1 sOut4 $end
$var wire 1 2 sOut3 $end
$var wire 1 3 sOut2 $end
$var wire 1 4 sOut1 $end
$var wire 1 ! sOut $end
$var wire 4 5 Q8 [3:0] $end
$var wire 4 6 Q7 [3:0] $end
$var wire 4 7 Q6 [3:0] $end
$var wire 4 8 Q5 [3:0] $end
$var wire 4 9 Q4 [3:0] $end
$var wire 4 : Q3 [3:0] $end
$var wire 4 ; Q2 [3:0] $end
$var wire 4 < Q1 [3:0] $end
$var wire 32 = Q [31:0] $end
$var wire 4 > D8 [3:0] $end
$var wire 4 ? D7 [3:0] $end
$var wire 4 @ D6 [3:0] $end
$var wire 4 A D5 [3:0] $end
$var wire 4 B D4 [3:0] $end
$var wire 4 C D3 [3:0] $end
$var wire 4 D D2 [3:0] $end
$var wire 4 E D1 [3:0] $end
$scope module registro1 $end
$var wire 4 F D [3:0] $end
$var wire 1 & clk $end
$var wire 1 % dir $end
$var wire 1 $ enb $end
$var wire 2 G modo [1:0] $end
$var wire 1 " sIn $end
$var reg 4 H Q [3:0] $end
$var reg 1 4 sOut $end
$upscope $end
$scope module registro2 $end
$var wire 4 I D [3:0] $end
$var wire 1 & clk $end
$var wire 1 % dir $end
$var wire 1 $ enb $end
$var wire 2 J modo [1:0] $end
$var wire 1 4 sIn $end
$var reg 4 K Q [3:0] $end
$var reg 1 3 sOut $end
$upscope $end
$scope module registro3 $end
$var wire 4 L D [3:0] $end
$var wire 1 & clk $end
$var wire 1 % dir $end
$var wire 1 $ enb $end
$var wire 2 M modo [1:0] $end
$var wire 1 3 sIn $end
$var reg 4 N Q [3:0] $end
$var reg 1 2 sOut $end
$upscope $end
$scope module registro4 $end
$var wire 4 O D [3:0] $end
$var wire 1 & clk $end
$var wire 1 % dir $end
$var wire 1 $ enb $end
$var wire 2 P modo [1:0] $end
$var wire 1 2 sIn $end
$var reg 4 Q Q [3:0] $end
$var reg 1 1 sOut $end
$upscope $end
$scope module registro5 $end
$var wire 4 R D [3:0] $end
$var wire 1 & clk $end
$var wire 1 % dir $end
$var wire 1 $ enb $end
$var wire 2 S modo [1:0] $end
$var wire 1 1 sIn $end
$var reg 4 T Q [3:0] $end
$var reg 1 0 sOut $end
$upscope $end
$scope module registro6 $end
$var wire 4 U D [3:0] $end
$var wire 1 & clk $end
$var wire 1 % dir $end
$var wire 1 $ enb $end
$var wire 2 V modo [1:0] $end
$var wire 1 0 sIn $end
$var reg 4 W Q [3:0] $end
$var reg 1 / sOut $end
$upscope $end
$scope module registro7 $end
$var wire 4 X D [3:0] $end
$var wire 1 & clk $end
$var wire 1 % dir $end
$var wire 1 $ enb $end
$var wire 2 Y modo [1:0] $end
$var wire 1 / sIn $end
$var reg 4 Z Q [3:0] $end
$var reg 1 . sOut $end
$upscope $end
$scope module registro8 $end
$var wire 4 [ D [3:0] $end
$var wire 1 & clk $end
$var wire 1 % dir $end
$var wire 1 $ enb $end
$var wire 2 \ modo [1:0] $end
$var wire 1 . sIn $end
$var reg 4 ] Q [3:0] $end
$var reg 1 ! sOut $end
$upscope $end
$upscope $end
$upscope $end
$enddefinitions $end
#0
$dumpvars
bx ]
b0 \
b1111 [
bx Z
b0 Y
b1 X
bx W
b0 V
b1 U
bx T
b0 S
b1 R
bx Q
b0 P
b1 O
bx N
b0 M
b1 L
bx K
b0 J
b1 I
bx H
b0 G
b1 F
b1 E
b1 D
b1 C
b1 B
b1 A
b1 @
b1 ?
b1111 >
bx =
bx <
bx ;
bx :
bx 9
bx 8
bx 7
bx 6
bx 5
x4
x3
x2
x1
x0
x/
x.
z-
b0 ,
b11110001000100010001000100010001 +
b0 *
b11110001000100010001000100010001 )
b11110001000100010001000100010001 (
bx '
0&
0%
1$
b0 #
1"
x!
$end
#2
bx1 '
bx1 =
bx1 <
bx1 H
1&
#4
0&
#6
bx11 '
bx11 =
bx11 <
bx11 H
1&
#8
0&
#10
bx111 '
bx111 =
bx111 <
bx111 H
1&
#12
0&
#14
bx1111 '
bx1111 =
b1111 <
b1111 H
1&
#16
0&
#18
14
1&
#20
0&
#22
bx11111 '
bx11111 =
bx1 ;
bx1 K
1&
#24
0&
#26
bx111111 '
bx111111 =
bx11 ;
bx11 K
1&
#28
0&
#30
bx1111111 '
bx1111111 =
bx111 ;
bx111 K
1&
#32
0&
#34
bx11111111 '
bx11111111 =
b1111 ;
b1111 K
1&
#36
0&
#38
13
1&
#40
0&
#42
bx111111111 '
bx111111111 =
bx1 :
bx1 N
1&
#44
0&
#46
bx1111111111 '
bx1111111111 =
bx11 :
bx11 N
1&
#48
0&
#50
bx11111111111 '
bx11111111111 =
bx111 :
bx111 N
1&
#52
0&
#54
bx111111111111 '
bx111111111111 =
b1111 :
b1111 N
1&
#56
0&
#58
12
1&
#60
0&
#62
bx1111111111111 '
bx1111111111111 =
bx1 9
bx1 Q
1&
#64
0&
#66
bx11111111111111 '
bx11111111111111 =
bx11 9
bx11 Q
1&
#68
0&
#70
bx111111111111111 '
bx111111111111111 =
bx111 9
bx111 Q
1&
#72
0&
#74
bx1111111111111111 '
bx1111111111111111 =
b1111 9
b1111 Q
1&
#76
0&
#78
11
1&
#80
0&
#82
bx11111111111111111 '
bx11111111111111111 =
bx1 8
bx1 T
1&
#84
0&
#86
bx111111111111111111 '
bx111111111111111111 =
bx11 8
bx11 T
1&
#88
0&
#90
bx1111111111111111111 '
bx1111111111111111111 =
bx111 8
bx111 T
1&
#92
0&
#94
bx11111111111111111111 '
bx11111111111111111111 =
b1111 8
b1111 T
1&
#96
0&
#98
10
1&
#100
0&
#102
bx111111111111111111111 '
bx111111111111111111111 =
bx1 7
bx1 W
1&
#104
0&
#106
bx1111111111111111111111 '
bx1111111111111111111111 =
bx11 7
bx11 W
1&
#108
0&
#110
bx11111111111111111111111 '
bx11111111111111111111111 =
bx111 7
bx111 W
1&
#112
0&
#114
bx111111111111111111111111 '
bx111111111111111111111111 =
b1111 7
b1111 W
1&
#116
0&
#118
1/
1&
#120
0&
#122
bx1111111111111111111111111 '
bx1111111111111111111111111 =
bx1 6
bx1 Z
1&
#124
0&
#126
bx11111111111111111111111111 '
bx11111111111111111111111111 =
bx11 6
bx11 Z
1&
#128
0&
#130
bx111111111111111111111111111 '
bx111111111111111111111111111 =
bx111 6
bx111 Z
1&
#132
0&
#134
bx1111111111111111111111111111 '
bx1111111111111111111111111111 =
b1111 6
b1111 Z
1&
#136
0&
#138
1.
1&
#140
0&
#142
bx11111111111111111111111111111 '
bx11111111111111111111111111111 =
bx1 5
bx1 ]
1&
#144
0&
#146
bx111111111111111111111111111111 '
bx111111111111111111111111111111 =
bx11 5
bx11 ]
1&
#148
0&
#150
bx1111111111111111111111111111111 '
bx1111111111111111111111111111111 =
bx111 5
bx111 ]
1&
#152
b10 #
b10 *
b10 ,
b10 G
b10 J
b10 M
b10 P
b10 S
b10 V
b10 Y
b10 \
0&
#154
04
b1 <
b1 H
03
b1 ;
b1 K
02
b1 :
b1 N
01
b1 9
b1 Q
00
b1 8
b1 T
0/
b1 7
b1 W
0.
b1 6
b1 Z
0!
b11110001000100010001000100010001 '
b11110001000100010001000100010001 =
b1111 5
b1111 ]
1&
#156
1%
b0 #
b0 *
b0 ,
b0 G
b0 J
b0 M
b0 P
b0 S
b0 V
b0 Y
b0 \
0&
#158
1!
b111 5
b111 ]
1.
b0 6
b0 Z
1/
b0 7
b0 W
10
b0 8
b0 T
11
b0 9
b0 Q
12
b0 :
b0 N
13
b0 ;
b0 K
14
b1110000000000000000000000001000 '
b1110000000000000000000000001000 =
b1000 <
b1000 H
1&
#160
0&
#162
04
b1100 <
b1100 H
03
b1000 ;
b1000 K
02
b1000 :
b1000 N
01
b1000 9
b1000 Q
00
b1000 8
b1000 T
0/
b1000 7
b1000 W
0.
b1000 6
b1000 Z
b10111000100010001000100010001100 '
b10111000100010001000100010001100 =
b1011 5
b1011 ]
1&
#164
0&
#166
b101 5
b101 ]
b100 6
b100 Z
b100 7
b100 W
b100 8
b100 T
b100 9
b100 Q
b100 :
b100 N
b100 ;
b100 K
b1010100010001000100010001001110 '
b1010100010001000100010001001110 =
b1110 <
b1110 H
1&
#168
0&
#170
b1111 <
b1111 H
b10 ;
b10 K
b10 :
b10 N
b10 9
b10 Q
b10 8
b10 T
b10 7
b10 W
b10 6
b10 Z
b100010001000100010001000101111 '
b100010001000100010001000101111 =
b10 5
b10 ]
1&
#172
0&
#174
0!
b1 5
b1 ]
b1 6
b1 Z
b1 7
b1 W
b1 8
b1 T
b1 9
b1 Q
b1 :
b1 N
b10001000100010001000100011111 '
b10001000100010001000100011111 =
b1 ;
b1 K
14
1&
#176
0&
#178
13
b1000 ;
b1000 K
12
b0 :
b0 N
11
b0 9
b0 Q
10
b0 8
b0 T
1/
b0 7
b0 W
1.
b0 6
b0 Z
1!
b10001111 '
b10001111 =
b0 5
b0 ]
1&
#180
0&
#182
0!
b1000 5
b1000 ]
0.
b1000 6
b1000 Z
0/
b1000 7
b1000 W
00
b1000 8
b1000 T
01
b1000 9
b1000 Q
02
b1000 :
b1000 N
03
b10001000100010001000100011001111 '
b10001000100010001000100011001111 =
b1100 ;
b1100 K
1&
#184
0&
#186
b1110 ;
b1110 K
b100 :
b100 N
b100 9
b100 Q
b100 8
b100 T
b100 7
b100 W
b100 6
b100 Z
b1000100010001000100010011101111 '
b1000100010001000100010011101111 =
b100 5
b100 ]
1&
#188
0&
#190
b10 5
b10 ]
b10 6
b10 Z
b10 7
b10 W
b10 8
b10 T
b10 9
b10 Q
b10 :
b10 N
b100010001000100010001011111111 '
b100010001000100010001011111111 =
b1111 ;
b1111 K
1&
#192
0&
#194
13
b1 :
b1 N
b1 9
b1 Q
b1 8
b1 T
b1 7
b1 W
b1 6
b1 Z
b10001000100010001000111111111 '
b10001000100010001000111111111 =
b1 5
b1 ]
1&
#196
0&
#198
1!
b0 5
b0 ]
1.
b0 6
b0 Z
1/
b0 7
b0 W
10
b0 8
b0 T
11
b0 9
b0 Q
12
b100011111111 '
b100011111111 =
b1000 :
b1000 N
1&
#200
0&
#202
02
b1100 :
b1100 N
01
b1000 9
b1000 Q
00
b1000 8
b1000 T
0/
b1000 7
b1000 W
0.
b1000 6
b1000 Z
0!
b10001000100010001000110011111111 '
b10001000100010001000110011111111 =
b1000 5
b1000 ]
1&
#204
0&
#206
b100 5
b100 ]
b100 6
b100 Z
b100 7
b100 W
b100 8
b100 T
b100 9
b100 Q
b1000100010001000100111011111111 '
b1000100010001000100111011111111 =
b1110 :
b1110 N
1&
#208
0&
#210
b1111 :
b1111 N
b10 9
b10 Q
b10 8
b10 T
b10 7
b10 W
b10 6
b10 Z
b100010001000100010111111111111 '
b100010001000100010111111111111 =
b10 5
b10 ]
1&
#212
0&
#214
b1 5
b1 ]
b1 6
b1 Z
b1 7
b1 W
b1 8
b1 T
b10001000100010001111111111111 '
b10001000100010001111111111111 =
b1 9
b1 Q
12
1&
#216
0&
#218
11
b1000 9
b1000 Q
10
b0 8
b0 T
1/
b0 7
b0 W
1.
b0 6
b0 Z
1!
b1000111111111111 '
b1000111111111111 =
b0 5
b0 ]
1&
#220
0&
#222
0!
b1000 5
b1000 ]
0.
b1000 6
b1000 Z
0/
b1000 7
b1000 W
00
b1000 8
b1000 T
01
b10001000100010001100111111111111 '
b10001000100010001100111111111111 =
b1100 9
b1100 Q
1&
#224
0&
#226
b1110 9
b1110 Q
b100 8
b100 T
b100 7
b100 W
b100 6
b100 Z
b1000100010001001110111111111111 '
b1000100010001001110111111111111 =
b100 5
b100 ]
1&
#228
0&
#230
b10 5
b10 ]
b10 6
b10 Z
b10 7
b10 W
b10 8
b10 T
b100010001000101111111111111111 '
b100010001000101111111111111111 =
b1111 9
b1111 Q
1&
#232
0&
#234
11
b1 8
b1 T
b1 7
b1 W
b1 6
b1 Z
b10001000100011111111111111111 '
b10001000100011111111111111111 =
b1 5
b1 ]
1&
#236
0&
#238
1!
b0 5
b0 ]
1.
b0 6
b0 Z
1/
b0 7
b0 W
10
b10001111111111111111 '
b10001111111111111111 =
b1000 8
b1000 T
1&
#240
0&
#242
00
b1100 8
b1100 T
0/
b1000 7
b1000 W
0.
b1000 6
b1000 Z
0!
b10001000100011001111111111111111 '
b10001000100011001111111111111111 =
b1000 5
b1000 ]
1&
#244
0&
#246
b100 5
b100 ]
b100 6
b100 Z
b100 7
b100 W
b1000100010011101111111111111111 '
b1000100010011101111111111111111 =
b1110 8
b1110 T
1&
#248
0&
#250
b1111 8
b1111 T
b10 7
b10 W
b10 6
b10 Z
b100010001011111111111111111111 '
b100010001011111111111111111111 =
b10 5
b10 ]
1&
#252
0&
#254
b1 5
b1 ]
b1 6
b1 Z
b10001000111111111111111111111 '
b10001000111111111111111111111 =
b1 7
b1 W
10
1&
#256
0&
#258
1/
b1000 7
b1000 W
1.
b0 6
b0 Z
1!
b100011111111111111111111 '
b100011111111111111111111 =
b0 5
b0 ]
1&
#260
0&
#262
0!
b1000 5
b1000 ]
0.
b1000 6
b1000 Z
0/
b10001000110011111111111111111111 '
b10001000110011111111111111111111 =
b1100 7
b1100 W
1&
#264
0&
#266
b1110 7
b1110 W
b100 6
b100 Z
b1000100111011111111111111111111 '
b1000100111011111111111111111111 =
b100 5
b100 ]
1&
#268
0&
#270
b10 5
b10 ]
b10 6
b10 Z
b100010111111111111111111111111 '
b100010111111111111111111111111 =
b1111 7
b1111 W
1&
#272
0&
#274
1/
b1 6
b1 Z
b10001111111111111111111111111 '
b10001111111111111111111111111 =
b1 5
b1 ]
1&
#276
0&
#278
1!
b0 5
b0 ]
1.
b1000111111111111111111111111 '
b1000111111111111111111111111 =
b1000 6
b1000 Z
1&
#280
0&
#282
0.
b1100 6
b1100 Z
0!
b10001100111111111111111111111111 '
b10001100111111111111111111111111 =
b1000 5
b1000 ]
1&
#284
0&
#286
b100 5
b100 ]
b1001110111111111111111111111111 '
b1001110111111111111111111111111 =
b1110 6
b1110 Z
1&
#288
0&
#290
b1111 6
b1111 Z
b101111111111111111111111111111 '
b101111111111111111111111111111 =
b10 5
b10 ]
1&
#292
0&
#294
b11111111111111111111111111111 '
b11111111111111111111111111111 =
b1 5
b1 ]
1.
1&
#296
0&
#298
1!
b10001111111111111111111111111111 '
b10001111111111111111111111111111 =
b1000 5
b1000 ]
1&
#300
0&
#302
0!
b11001111111111111111111111111111 '
b11001111111111111111111111111111 =
b1100 5
b1100 ]
1&
#304
0&
#306
b11101111111111111111111111111111 '
b11101111111111111111111111111111 =
b1110 5
b1110 ]
1&
#308
b10 #
b10 *
b10 ,
b10 G
b10 J
b10 M
b10 P
b10 S
b10 V
b10 Y
b10 \
0&
#310
b1111 5
b1111 ]
0.
b1 6
b1 Z
0/
b1 7
b1 W
00
b1 8
b1 T
01
b1 9
b1 Q
02
b1 :
b1 N
03
b1 ;
b1 K
04
b11110001000100010001000100010001 '
b11110001000100010001000100010001 =
b1 <
b1 H
1&
#312
0%
b1 #
b1 *
b1 ,
b1 G
b1 J
b1 M
b1 P
b1 S
b1 V
b1 Y
b1 \
0&
#314
b10 <
b10 H
b10 ;
b10 K
b10 :
b10 N
b10 9
b10 Q
b10 8
b10 T
b10 7
b10 W
b11110010001000100010001000100010 '
b11110010001000100010001000100010 =
b10 6
b10 Z
1&
#316
0&
#318
b100 6
b100 Z
b100 7
b100 W
b100 8
b100 T
b100 9
b100 Q
b100 :
b100 N
b100 ;
b100 K
b11110100010001000100010001000100 '
b11110100010001000100010001000100 =
b100 <
b100 H
1&
#320
0&
#322
b1000 <
b1000 H
b1000 ;
b1000 K
b1000 :
b1000 N
b1000 9
b1000 Q
b1000 8
b1000 T
b1000 7
b1000 W
b11111000100010001000100010001000 '
b11111000100010001000100010001000 =
b1000 6
b1000 Z
1&
#324
0&
#326
b1 6
b1 Z
b1 7
b1 W
b1 8
b1 T
b1 9
b1 Q
b1 :
b1 N
b1 ;
b1 K
b11110001000100010001000100010001 '
b11110001000100010001000100010001 =
b1 <
b1 H
1&
#328
0&
#330
b10 <
b10 H
b10 ;
b10 K
b10 :
b10 N
b10 9
b10 Q
b10 8
b10 T
b10 7
b10 W
b11110010001000100010001000100010 '
b11110010001000100010001000100010 =
b10 6
b10 Z
1&
#332
0&
#334
b100 6
b100 Z
b100 7
b100 W
b100 8
b100 T
b100 9
b100 Q
b100 :
b100 N
b100 ;
b100 K
b11110100010001000100010001000100 '
b11110100010001000100010001000100 =
b100 <
b100 H
1&
#336
0&
#338
b1000 <
b1000 H
b1000 ;
b1000 K
b1000 :
b1000 N
b1000 9
b1000 Q
b1000 8
b1000 T
b1000 7
b1000 W
b11111000100010001000100010001000 '
b11111000100010001000100010001000 =
b1000 6
b1000 Z
1&
#340
0&
#342
b1 6
b1 Z
b1 7
b1 W
b1 8
b1 T
b1 9
b1 Q
b1 :
b1 N
b1 ;
b1 K
b11110001000100010001000100010001 '
b11110001000100010001000100010001 =
b1 <
b1 H
1&
#344
0&
#346
b10 <
b10 H
b10 ;
b10 K
b10 :
b10 N
b10 9
b10 Q
b10 8
b10 T
b10 7
b10 W
b11110010001000100010001000100010 '
b11110010001000100010001000100010 =
b10 6
b10 Z
1&
#348
0&
#350
b100 6
b100 Z
b100 7
b100 W
b100 8
b100 T
b100 9
b100 Q
b100 :
b100 N
b100 ;
b100 K
b11110100010001000100010001000100 '
b11110100010001000100010001000100 =
b100 <
b100 H
1&
#352
0&
#354
b1000 <
b1000 H
b1000 ;
b1000 K
b1000 :
b1000 N
b1000 9
b1000 Q
b1000 8
b1000 T
b1000 7
b1000 W
b11111000100010001000100010001000 '
b11111000100010001000100010001000 =
b1000 6
b1000 Z
1&
#356
0&
#358
b1 6
b1 Z
b1 7
b1 W
b1 8
b1 T
b1 9
b1 Q
b1 :
b1 N
b1 ;
b1 K
b11110001000100010001000100010001 '
b11110001000100010001000100010001 =
b1 <
b1 H
1&
#360
0&
#362
b10 <
b10 H
b10 ;
b10 K
b10 :
b10 N
b10 9
b10 Q
b10 8
b10 T
b10 7
b10 W
b11110010001000100010001000100010 '
b11110010001000100010001000100010 =
b10 6
b10 Z
1&
#364
0&
#366
b100 6
b100 Z
b100 7
b100 W
b100 8
b100 T
b100 9
b100 Q
b100 :
b100 N
b100 ;
b100 K
b11110100010001000100010001000100 '
b11110100010001000100010001000100 =
b100 <
b100 H
1&
#368
0&
#370
b1000 <
b1000 H
b1000 ;
b1000 K
b1000 :
b1000 N
b1000 9
b1000 Q
b1000 8
b1000 T
b1000 7
b1000 W
b11111000100010001000100010001000 '
b11111000100010001000100010001000 =
b1000 6
b1000 Z
1&
#372
0&
#374
b1 6
b1 Z
b1 7
b1 W
b1 8
b1 T
b1 9
b1 Q
b1 :
b1 N
b1 ;
b1 K
b11110001000100010001000100010001 '
b11110001000100010001000100010001 =
b1 <
b1 H
1&
#376
0&
#378
b10 <
b10 H
b10 ;
b10 K
b10 :
b10 N
b10 9
b10 Q
b10 8
b10 T
b10 7
b10 W
b11110010001000100010001000100010 '
b11110010001000100010001000100010 =
b10 6
b10 Z
1&
#380
0&
#382
b100 6
b100 Z
b100 7
b100 W
b100 8
b100 T
b100 9
b100 Q
b100 :
b100 N
b100 ;
b100 K
b11110100010001000100010001000100 '
b11110100010001000100010001000100 =
b100 <
b100 H
1&
#384
0&
#386
b1000 <
b1000 H
b1000 ;
b1000 K
b1000 :
b1000 N
b1000 9
b1000 Q
b1000 8
b1000 T
b1000 7
b1000 W
b11111000100010001000100010001000 '
b11111000100010001000100010001000 =
b1000 6
b1000 Z
1&
#388
0&
#390
b1 6
b1 Z
b1 7
b1 W
b1 8
b1 T
b1 9
b1 Q
b1 :
b1 N
b1 ;
b1 K
b11110001000100010001000100010001 '
b11110001000100010001000100010001 =
b1 <
b1 H
1&
#392
0&
#394
b10 <
b10 H
b10 ;
b10 K
b10 :
b10 N
b10 9
b10 Q
b10 8
b10 T
b10 7
b10 W
b11110010001000100010001000100010 '
b11110010001000100010001000100010 =
b10 6
b10 Z
1&
#396
0&
#398
b100 6
b100 Z
b100 7
b100 W
b100 8
b100 T
b100 9
b100 Q
b100 :
b100 N
b100 ;
b100 K
b11110100010001000100010001000100 '
b11110100010001000100010001000100 =
b100 <
b100 H
1&
#400
0&
#402
b1000 <
b1000 H
b1000 ;
b1000 K
b1000 :
b1000 N
b1000 9
b1000 Q
b1000 8
b1000 T
b1000 7
b1000 W
b11111000100010001000100010001000 '
b11111000100010001000100010001000 =
b1000 6
b1000 Z
1&
#404
0&
#406
b1 6
b1 Z
b1 7
b1 W
b1 8
b1 T
b1 9
b1 Q
b1 :
b1 N
b1 ;
b1 K
b11110001000100010001000100010001 '
b11110001000100010001000100010001 =
b1 <
b1 H
1&
#408
0&
#410
b10 <
b10 H
b10 ;
b10 K
b10 :
b10 N
b10 9
b10 Q
b10 8
b10 T
b10 7
b10 W
b11110010001000100010001000100010 '
b11110010001000100010001000100010 =
b10 6
b10 Z
1&
#412
0&
#414
b100 6
b100 Z
b100 7
b100 W
b100 8
b100 T
b100 9
b100 Q
b100 :
b100 N
b100 ;
b100 K
b11110100010001000100010001000100 '
b11110100010001000100010001000100 =
b100 <
b100 H
1&
#416
0&
#418
b1000 <
b1000 H
b1000 ;
b1000 K
b1000 :
b1000 N
b1000 9
b1000 Q
b1000 8
b1000 T
b1000 7
b1000 W
b11111000100010001000100010001000 '
b11111000100010001000100010001000 =
b1000 6
b1000 Z
1&
#420
0&
#422
b1 6
b1 Z
b1 7
b1 W
b1 8
b1 T
b1 9
b1 Q
b1 :
b1 N
b1 ;
b1 K
b11110001000100010001000100010001 '
b11110001000100010001000100010001 =
b1 <
b1 H
1&
#424
0&
#426
b10 <
b10 H
b10 ;
b10 K
b10 :
b10 N
b10 9
b10 Q
b10 8
b10 T
b10 7
b10 W
b11110010001000100010001000100010 '
b11110010001000100010001000100010 =
b10 6
b10 Z
1&
#428
0&
#430
b100 6
b100 Z
b100 7
b100 W
b100 8
b100 T
b100 9
b100 Q
b100 :
b100 N
b100 ;
b100 K
b11110100010001000100010001000100 '
b11110100010001000100010001000100 =
b100 <
b100 H
1&
#432
0&
#434
b1000 <
b1000 H
b1000 ;
b1000 K
b1000 :
b1000 N
b1000 9
b1000 Q
b1000 8
b1000 T
b1000 7
b1000 W
b11111000100010001000100010001000 '
b11111000100010001000100010001000 =
b1000 6
b1000 Z
1&
#436
0&
#438
b1 6
b1 Z
b1 7
b1 W
b1 8
b1 T
b1 9
b1 Q
b1 :
b1 N
b1 ;
b1 K
b11110001000100010001000100010001 '
b11110001000100010001000100010001 =
b1 <
b1 H
1&
#440
0&
#442
b10 <
b10 H
b10 ;
b10 K
b10 :
b10 N
b10 9
b10 Q
b10 8
b10 T
b10 7
b10 W
b11110010001000100010001000100010 '
b11110010001000100010001000100010 =
b10 6
b10 Z
1&
#444
0&
#446
b100 6
b100 Z
b100 7
b100 W
b100 8
b100 T
b100 9
b100 Q
b100 :
b100 N
b100 ;
b100 K
b11110100010001000100010001000100 '
b11110100010001000100010001000100 =
b100 <
b100 H
1&
#448
0&
#450
b1000 <
b1000 H
b1000 ;
b1000 K
b1000 :
b1000 N
b1000 9
b1000 Q
b1000 8
b1000 T
b1000 7
b1000 W
b11111000100010001000100010001000 '
b11111000100010001000100010001000 =
b1000 6
b1000 Z
1&
#452
0&
