tarea3/compare/definitions.v
wire [1:0] modo;
wire [3:0] D;
wire [3:0] QA;
wire [3:0] QB;
wire [3:0] QC;

tarea3/compare/contadorC.v
/* Generated by Yosys 0.7 (git sha1 61f6811, gcc 6.2.0-11ubuntu1 -O2 -fdebug-prefix-map=/build/yosys-OIL3SR/yosys-0.7=. -fstack-protector-strong -fPIC -Os) */

module countC(enable, clk, modo, D, rco, Q);
  wire [3:0] _000_;
  wire _001_;
  wire [31:0] _002_;
  wire [1:0] _003_;
  wire [1:0] _004_;
  wire [1:0] _005_;
  wire [1:0] _006_;
  wire [1:0] _007_;
  wire [1:0] _008_;
  wire [1:0] _009_;
  wire [1:0] _010_;
  wire _011_;
  wire [1:0] _012_;
  wire _013_;
  wire [3:0] _014_;
  wire [1:0] _015_;
  wire _016_;
  wire _017_;
  wire _018_;
  wire _019_;
  wire _020_;
  wire _021_;
  wire _022_;
  wire _023_;
  wire _024_;
  wire [3:0] _025_;
  wire _026_;
  wire _027_;
  wire _028_;
  wire _029_;
  wire _030_;
  wire _031_;
  wire [15:0] _032_;
  wire [3:0] _033_;
  wire [3:0] _034_;
  wire [31:0] _035_;
  wire [31:0] _036_;
  wire [31:0] _037_;
  wire _038_;
  wire [31:0] _039_;
  wire [31:0] _040_;
  wire _041_;
  wire _042_;
  wire _043_;
  input [3:0] D;
  output [3:0] Q;
  reg [3:0] Q;
  input clk;
  input enable;
  input [1:0] modo;
  output rco;
  reg rco;
  assign _003_[0] = _002_[0] | Q[1];
  assign _003_[1] = Q[2] | Q[3];
  assign _020_ = _003_[0] | _003_[1];
  assign _004_[0] = _002_[0] | _014_[1];
  assign _004_[1] = _014_[2] | _014_[3];
  assign _016_ = _004_[0] | _004_[1];
  assign _017_ = _015_[0] | _015_[1];
  assign _018_ = modo[0] | _015_[1];
  assign _019_ = _015_[0] | modo[1];
  assign _005_[1] = _025_[2] | _025_[3];
  assign _026_ = _005_[0] | _005_[1];
  assign _038_ = _006_[0] | _006_[1];
  assign _007_[0] = _032_[2] | _032_[6];
  assign _007_[1] = _032_[10] | _032_[14];
  assign _033_[2] = _007_[0] | _007_[1];
  assign _008_[0] = _032_[3] | _032_[7];
  assign _008_[1] = _032_[11] | _032_[15];
  assign _033_[3] = _008_[0] | _008_[1];
  assign _009_[0] = _032_[1] | _032_[5];
  assign _009_[1] = _032_[9] | _032_[13];
  assign _033_[1] = _009_[0] | _009_[1];
  assign _010_[0] = _032_[0] | _032_[4];
  assign _010_[1] = _032_[8] | _032_[12];
  assign _033_[0] = _010_[0] | _010_[1];
  assign _006_[0] = _028_ | _029_;
  assign _006_[1] = _030_ | _031_;
  assign _011_ = modo[0] | modo[1];
  assign _012_[0] = Q[0] | Q[1];
  assign _013_ = _012_[0] | _003_[1];
  assign _023_ = ~_020_;
  assign _021_ = ~_016_;
  assign _028_ = ~_017_;
  assign _029_ = ~_018_;
  assign _030_ = ~_019_;
  assign _031_ = ~_011_;
  assign _022_ = ~_013_;
  assign _024_ = _022_ | _023_;
  assign _001_ = enable ? _027_ : 1'b0;
  assign _000_[0] = enable ? _034_[0] : 1'b0;
  assign _000_[1] = enable ? _034_[1] : 1'b0;
  assign _000_[2] = enable ? _034_[2] : 1'b0;
  assign _000_[3] = enable ? _034_[3] : 1'b0;
  assign _027_ = _038_ ? _026_ : rco;
  assign _034_[0] = _038_ ? _033_[0] : Q[0];
  assign _034_[1] = _038_ ? _033_[1] : Q[1];
  assign _034_[2] = _038_ ? _033_[2] : Q[2];
  assign _034_[3] = _038_ ? _033_[3] : Q[3];
  always @(posedge clk)
      Q[0] <= _000_[0];
  always @(posedge clk)
      Q[1] <= _000_[1];
  always @(posedge clk)
      Q[2] <= _000_[2];
  always @(posedge clk)
      Q[3] <= _000_[3];
  always @(posedge clk)
      rco <= _001_;
  assign _042_ = _014_[2] & _039_[1];
  assign _039_[1] = Q[1] | _041_;
  assign _039_[2] = Q[2] | _042_;
  assign _043_ = _014_[2] & _037_[1];
  assign _040_[2] = Q[2] | _043_;
  assign _037_[1] = Q[1] & Q[0];
  assign _037_[2] = Q[2] & _037_[1];
  assign _015_[1] = modo[1] ^ 1'b1;
  assign _015_[0] = modo[0] ^ 1'b1;
  assign _025_[3] = _021_ & _031_;
  assign _025_[2] = _022_ & _030_;
  assign _005_[0] = _024_ & _029_;
  assign _032_[12] = _002_[0] & _031_;
  assign _032_[13] = _002_[1] & _031_;
  assign _032_[14] = _002_[2] & _031_;
  assign _032_[15] = _002_[3] & _031_;
  assign _032_[8] = _002_[0] & _030_;
  assign _032_[9] = _035_[1] & _030_;
  assign _032_[10] = _035_[2] & _030_;
  assign _032_[11] = _035_[3] & _030_;
  assign _032_[4] = _002_[0] & _029_;
  assign _032_[5] = _002_[1] & _029_;
  assign _032_[6] = _036_[2] & _029_;
  assign _032_[7] = _036_[3] & _029_;
  assign _032_[0] = D[0] & _028_;
  assign _032_[1] = D[1] & _028_;
  assign _032_[2] = D[2] & _028_;
  assign _032_[3] = D[3] & _028_;
  assign _014_[1] = Q[1] ^ 1'b1;
  assign _002_[0] = Q[0] ^ 1'b1;
  assign _035_[1] = _014_[1] ^ Q[0];
  assign _035_[2] = _014_[2] ^ _039_[1];
  assign _035_[3] = _014_[3] ^ _039_[2];
  assign _014_[2] = Q[2] ^ 1'b1;
  assign _014_[3] = Q[3] ^ 1'b1;
  assign _002_[1] = Q[1] ^ Q[0];
  assign _036_[2] = _014_[2] ^ _037_[1];
  assign _036_[3] = _014_[3] ^ _040_[2];
  assign _002_[2] = Q[2] ^ _037_[1];
  assign _002_[3] = Q[3] ^ _037_[2];
  assign _041_ = _014_[1] & Q[0];
endmodule

tarea3/compare/contadorB.v
/* Generated by Yosys 0.7 (git sha1 61f6811, gcc 6.2.0-11ubuntu1 -O2 -fdebug-prefix-map=/build/yosys-OIL3SR/yosys-0.7=. -fstack-protector-strong -fPIC -Os) */

module countB(enable, clk, modo, D, rco, Q);
  wire [3:0] _000_;
  wire _001_;
  wire [31:0] _002_;
  wire [1:0] _003_;
  wire [1:0] _004_;
  wire [1:0] _005_;
  wire [1:0] _006_;
  wire [1:0] _007_;
  wire [1:0] _008_;
  wire [1:0] _009_;
  wire [1:0] _010_;
  wire [1:0] _011_;
  wire [1:0] _012_;
  wire [1:0] _013_;
  wire _014_;
  wire _015_;
  wire [3:0] _016_;
  wire [3:0] _017_;
  wire [3:0] _018_;
  wire [1:0] _019_;
  wire _020_;
  wire _021_;
  wire _022_;
  wire _023_;
  wire _024_;
  wire _025_;
  wire _026_;
  wire _027_;
  wire _028_;
  wire _029_;
  wire _030_;
  wire _031_;
  wire _032_;
  wire _033_;
  wire _034_;
  wire _035_;
  wire _036_;
  wire _037_;
  wire _038_;
  wire _039_;
  wire _040_;
  wire _041_;
  wire _042_;
  wire _043_;
  wire _044_;
  wire _045_;
  wire _046_;
  wire _047_;
  wire _048_;
  wire _049_;
  wire _050_;
  wire [3:0] _051_;
  wire _052_;
  wire _053_;
  wire _054_;
  wire _055_;
  wire _056_;
  wire _057_;
  wire [15:0] _058_;
  wire [3:0] _059_;
  wire [3:0] _060_;
  wire [31:0] _061_;
  wire [31:0] _062_;
  wire [31:0] _063_;
  wire _064_;
  wire [31:0] _065_;
  wire [31:0] _066_;
  wire _067_;
  wire _068_;
  wire _069_;
  input [3:0] D;
  output [3:0] Q;
  reg [3:0] Q;
  input clk;
  input enable;
  input [1:0] modo;
  output rco;
  reg rco;
  assign _020_ = _003_[0] | _003_[1];
  assign _004_[0] = _002_[0] | Q[1];
  assign _021_ = _004_[0] | _004_[1];
  assign _004_[1] = Q[2] | Q[3];
  assign _022_ = _005_[0] | _004_[1];
  assign _023_ = _006_[0] | _006_[1];
  assign _024_ = _005_[0] | _003_[1];
  assign _003_[1] = Q[2] | _016_[3];
  assign _025_ = _006_[0] | _003_[1];
  assign _005_[0] = Q[0] | _017_[1];
  assign _026_ = _005_[0] | _006_[1];
  assign _003_[0] = Q[0] | Q[1];
  assign _006_[1] = _018_[2] | Q[3];
  assign _027_ = _003_[0] | _006_[1];
  assign _006_[0] = _002_[0] | _017_[1];
  assign _007_[1] = _018_[2] | _016_[3];
  assign _028_ = _006_[0] | _007_[1];
  assign _029_ = _019_[0] | _019_[1];
  assign _030_ = modo[0] | _019_[1];
  assign _031_ = _019_[0] | modo[1];
  assign _008_[0] = _051_[0] | _051_[1];
  assign _008_[1] = _051_[2] | _051_[3];
  assign _052_ = _008_[0] | _008_[1];
  assign _064_ = _009_[0] | _009_[1];
  assign _010_[0] = _058_[2] | _058_[6];
  assign _010_[1] = _058_[10] | _058_[14];
  assign _059_[2] = _010_[0] | _010_[1];
  assign _011_[0] = _058_[3] | _058_[7];
  assign _011_[1] = _058_[11] | _058_[15];
  assign _059_[3] = _011_[0] | _011_[1];
  assign _012_[0] = _058_[1] | _058_[5];
  assign _012_[1] = _058_[9] | _058_[13];
  assign _059_[1] = _012_[0] | _012_[1];
  assign _013_[0] = _058_[0] | _058_[4];
  assign _013_[1] = _058_[8] | _058_[12];
  assign _059_[0] = _013_[0] | _013_[1];
  assign _009_[0] = _054_ | _055_;
  assign _009_[1] = _056_ | _057_;
  assign _014_ = _003_[0] | _004_[1];
  assign _015_ = modo[0] | modo[1];
  assign _033_ = ~_020_;
  assign _035_ = ~_014_;
  assign _034_ = ~_021_;
  assign _036_ = ~_022_;
  assign _037_ = ~_023_;
  assign _038_ = ~_024_;
  assign _039_ = ~_025_;
  assign _040_ = ~_026_;
  assign _041_ = ~_027_;
  assign _032_ = ~_028_;
  assign _054_ = ~_029_;
  assign _055_ = ~_030_;
  assign _056_ = ~_031_;
  assign _057_ = ~_015_;
  assign _042_ = _035_ | _034_;
  assign _043_ = _042_ | _036_;
  assign _044_ = _043_ | _037_;
  assign _045_ = _038_ | _039_;
  assign _046_ = _045_ | _040_;
  assign _047_ = _046_ | _041_;
  assign _050_ = ~_047_;
  assign _001_ = enable ? _053_ : 1'b1;
  assign _000_[0] = enable ? _060_[0] : 1'b0;
  assign _000_[1] = enable ? _060_[1] : 1'b0;
  assign _000_[2] = enable ? _060_[2] : 1'b0;
  assign _000_[3] = enable ? _060_[3] : 1'b0;
  assign _053_ = _064_ ? _052_ : rco;
  assign _060_[0] = _064_ ? _059_[0] : Q[0];
  assign _060_[1] = _064_ ? _059_[1] : Q[1];
  assign _060_[2] = _064_ ? _059_[2] : Q[2];
  assign _060_[3] = _064_ ? _059_[3] : Q[3];
  always @(posedge clk)
      Q[0] <= _000_[0];
  always @(posedge clk)
      Q[1] <= _000_[1];
  always @(posedge clk)
      Q[2] <= _000_[2];
  always @(posedge clk)
      Q[3] <= _000_[3];
  always @(posedge clk)
      rco <= _001_;
  assign _067_ = _017_[1] & Q[0];
  assign _068_ = _018_[2] & _065_[1];
  assign _048_ = _032_ | _033_;
  assign _065_[1] = Q[1] | _067_;
  assign _049_ = _048_ | _034_;
  assign _065_[2] = Q[2] | _068_;
  assign _069_ = _018_[2] & _063_[1];
  assign _066_[2] = Q[2] | _069_;
  assign _063_[1] = Q[1] & Q[0];
  assign _063_[2] = Q[2] & _063_[1];
  assign _019_[1] = modo[1] ^ 1'b1;
  assign _019_[0] = modo[0] ^ 1'b1;
  assign _051_[3] = _049_ & _057_;
  assign _051_[2] = _014_ & _056_;
  assign _051_[1] = _044_ & _055_;
  assign _051_[0] = _050_ & _054_;
  assign _058_[12] = _002_[0] & _057_;
  assign _058_[13] = _002_[1] & _057_;
  assign _058_[14] = _002_[2] & _057_;
  assign _058_[15] = _002_[3] & _057_;
  assign _058_[8] = _002_[0] & _056_;
  assign _058_[9] = _061_[1] & _056_;
  assign _058_[10] = _061_[2] & _056_;
  assign _058_[11] = _061_[3] & _056_;
  assign _058_[4] = _002_[0] & _055_;
  assign _058_[5] = _002_[1] & _055_;
  assign _058_[6] = _062_[2] & _055_;
  assign _058_[7] = _062_[3] & _055_;
  assign _058_[0] = D[0] & _054_;
  assign _058_[1] = D[1] & _054_;
  assign _058_[2] = D[2] & _054_;
  assign _058_[3] = D[3] & _054_;
  assign _017_[1] = Q[1] ^ 1'b1;
  assign _018_[2] = Q[2] ^ 1'b1;
  assign _016_[3] = Q[3] ^ 1'b1;
  assign _002_[0] = Q[0] ^ 1'b1;
  assign _061_[1] = _017_[1] ^ Q[0];
  assign _061_[2] = _018_[2] ^ _065_[1];
  assign _061_[3] = _016_[3] ^ _065_[2];
  assign _062_[2] = _018_[2] ^ _063_[1];
  assign _062_[3] = _016_[3] ^ _066_[2];
  assign _002_[1] = Q[1] ^ Q[0];
  assign _002_[2] = Q[2] ^ _063_[1];
  assign _002_[3] = Q[3] ^ _063_[2];
endmodule

tarea3/compare/contadorA.v
/* Generated by Yosys 0.7 (git sha1 61f6811, gcc 6.2.0-11ubuntu1 -O2 -fdebug-prefix-map=/build/yosys-OIL3SR/yosys-0.7=. -fstack-protector-strong -fPIC -Os) */

module countA(enable, clk, modo, D, rco, Q);
  wire [3:0] _000_;
  wire _001_;
  wire [31:0] _002_;
  wire [1:0] _003_;
  wire [1:0] _004_;
  wire [1:0] _005_;
  wire [1:0] _006_;
  wire [1:0] _007_;
  wire [1:0] _008_;
  wire [1:0] _009_;
  wire [1:0] _010_;
  wire [1:0] _011_;
  wire _012_;
  wire [1:0] _013_;
  wire _014_;
  wire [3:0] _015_;
  wire [3:0] _016_;
  wire [1:0] _017_;
  wire _018_;
  wire _019_;
  wire _020_;
  wire _021_;
  wire _022_;
  wire _023_;
  wire _024_;
  wire _025_;
  wire _026_;
  wire _027_;
  wire _028_;
  wire _029_;
  wire [3:0] _030_;
  wire _031_;
  wire _032_;
  wire _033_;
  wire _034_;
  wire _035_;
  wire [15:0] _036_;
  wire [3:0] _037_;
  wire [3:0] _038_;
  wire [31:0] _039_;
  wire [31:0] _040_;
  wire [31:0] _041_;
  wire _042_;
  wire [31:0] _043_;
  wire [31:0] _044_;
  wire _045_;
  wire _046_;
  wire _047_;
  input [3:0] D;
  output [3:0] Q;
  reg [3:0] Q;
  input clk;
  input enable;
  input [1:0] modo;
  output rco;
  reg rco;
  assign _003_[0] = _002_[0] | Q[1];
  assign _018_ = _003_[0] | _003_[1];
  assign _004_[0] = Q[0] | _015_[1];
  assign _003_[1] = Q[2] | Q[3];
  assign _019_ = _004_[0] | _003_[1];
  assign _005_[0] = _002_[0] | _015_[1];
  assign _005_[1] = _016_[2] | _016_[3];
  assign _020_ = _005_[0] | _005_[1];
  assign _021_ = _017_[0] | _017_[1];
  assign _022_ = modo[0] | _017_[1];
  assign _023_ = _017_[0] | modo[1];
  assign _006_[0] = _030_[0] | _030_[1];
  assign _006_[1] = _030_[2] | _030_[3];
  assign _031_ = _006_[0] | _006_[1];
  assign _042_ = _007_[0] | _007_[1];
  assign _008_[0] = _036_[2] | _036_[6];
  assign _008_[1] = _036_[10] | _036_[14];
  assign _037_[2] = _008_[0] | _008_[1];
  assign _009_[0] = _036_[3] | _036_[7];
  assign _009_[1] = _036_[11] | _036_[15];
  assign _037_[3] = _009_[0] | _009_[1];
  assign _010_[0] = _036_[1] | _036_[5];
  assign _010_[1] = _036_[9] | _036_[13];
  assign _037_[1] = _010_[0] | _010_[1];
  assign _011_[0] = _036_[0] | _036_[4];
  assign _011_[1] = _036_[8] | _036_[12];
  assign _037_[0] = _011_[0] | _011_[1];
  assign _007_[0] = _030_[0] | _033_;
  assign _007_[1] = _034_ | _035_;
  assign _012_ = modo[0] | modo[1];
  assign _013_[0] = Q[0] | Q[1];
  assign _014_ = _013_[0] | _003_[1];
  assign _027_ = ~_018_;
  assign _026_ = ~_019_;
  assign _024_ = ~_020_;
  assign _030_[0] = ~_021_;
  assign _033_ = ~_022_;
  assign _034_ = ~_023_;
  assign _035_ = ~_012_;
  assign _025_ = ~_014_;
  assign _028_ = _025_ | _027_;
  assign _029_ = _028_ | _026_;
  assign _001_ = enable ? _032_ : 1'b0;
  assign _000_[0] = enable ? _038_[0] : 1'b0;
  assign _000_[1] = enable ? _038_[1] : 1'b0;
  assign _000_[2] = enable ? _038_[2] : 1'b0;
  assign _000_[3] = enable ? _038_[3] : 1'b0;
  assign _032_ = _042_ ? _031_ : rco;
  assign _038_[0] = _042_ ? _037_[0] : Q[0];
  assign _038_[1] = _042_ ? _037_[1] : Q[1];
  assign _038_[2] = _042_ ? _037_[2] : Q[2];
  assign _038_[3] = _042_ ? _037_[3] : Q[3];
  always @(posedge clk)
      Q[0] <= _000_[0];
  always @(posedge clk)
      Q[1] <= _000_[1];
  always @(posedge clk)
      Q[2] <= _000_[2];
  always @(posedge clk)
      Q[3] <= _000_[3];
  always @(posedge clk)
      rco <= _001_;
  assign _045_ = _015_[1] & Q[0];
  assign _046_ = _016_[2] & _043_[1];
  assign _043_[1] = Q[1] | _045_;
  assign _043_[2] = Q[2] | _046_;
  assign _041_[1] = Q[1] & Q[0];
  assign _047_ = _016_[2] & _041_[1];
  assign _044_[2] = Q[2] | _047_;
  assign _041_[2] = Q[2] & _041_[1];
  assign _017_[1] = modo[1] ^ 1'b1;
  assign _017_[0] = modo[0] ^ 1'b1;
  assign _030_[3] = _024_ & _035_;
  assign _030_[2] = _025_ & _034_;
  assign _030_[1] = _029_ & _033_;
  assign _036_[12] = _002_[0] & _035_;
  assign _036_[13] = _002_[1] & _035_;
  assign _036_[14] = _002_[2] & _035_;
  assign _036_[15] = _002_[3] & _035_;
  assign _036_[8] = _002_[0] & _034_;
  assign _036_[9] = _039_[1] & _034_;
  assign _036_[10] = _039_[2] & _034_;
  assign _036_[11] = _039_[3] & _034_;
  assign _036_[4] = _002_[0] & _033_;
  assign _036_[5] = _002_[1] & _033_;
  assign _036_[6] = _040_[2] & _033_;
  assign _036_[7] = _040_[3] & _033_;
  assign _036_[0] = D[0] & _030_[0];
  assign _036_[1] = D[1] & _030_[0];
  assign _036_[2] = D[2] & _030_[0];
  assign _036_[3] = D[3] & _030_[0];
  assign _015_[1] = Q[1] ^ 1'b1;
  assign _016_[2] = Q[2] ^ 1'b1;
  assign _016_[3] = Q[3] ^ 1'b1;
  assign _002_[0] = Q[0] ^ 1'b1;
  assign _039_[1] = _015_[1] ^ Q[0];
  assign _039_[2] = _016_[2] ^ _043_[1];
  assign _039_[3] = _016_[3] ^ _043_[2];
  assign _040_[2] = _016_[2] ^ _041_[1];
  assign _040_[3] = _016_[3] ^ _044_[2];
  assign _002_[1] = Q[1] ^ Q[0];
  assign _002_[2] = Q[2] ^ _041_[1];
  assign _002_[3] = Q[3] ^ _041_[2];
endmodule

tarea3/driver.v
//Init task for clean output signals
task drv_init;
  begin
    @(negedge clk) begin
      enable = 1;
      D = 4'b0000;
      modo = 2'b11;
    end
    @(negedge clk)
      enable = 1;
    @(negedge clk)
      enable = 1;
  end
endtask

//Drive request to the arbiter
task drv_request;
  begin

  input integer iteration;
  @(negedge clk) begin
    enable = $random;
    D = 4'b0000;
    modo = 2'b00;
  end
    repeat (iteration) begin
    @(negedge clk) begin
        D = 4'b0000;
    end
  end
endtask

tarea3/scoreboard.v
`timescale 1ns/1ps
//Scoreboard
module scoreboard (D, modo, enable, clk) ;

input [3:0] D;
input clk;
input enable;
input [1:0] modo;



//wire  sb_rco;
reg sb_rco;
reg [3:0] sb_Q;

//UPDATE THIS SECTION
always @(posedge clk)
begin
  if (enable == 1'b1) begin

    if (modo == 2'b00) begin//Check add 1

      if (sb_rco == 1'b1) begin //Check carry out
        sb_rco = 1'b0;
      end

      if (sb_Q < 4'b1111) begin //Check if add
        sb_Q[3:0] = sb_Q + 4'b0001;
      end
      else begin //Rebase
        sb_Q = 4'b0000;
        sb_rco = 1'b1;
      end
    end

    if (modo == 2'b01) begin //Check substract 1

      if (sb_rco == 1'b1) begin //Check carry out
        sb_rco = 1'b0;
      end

      if (sb_Q > 4'b0000) begin //Check if add
        sb_Q[3:0] = sb_Q - 4'b0001;
      end
      else begin //Rebase
        sb_Q = 4'b1111;
        sb_rco = 1'b1;
      end

    end
    if (modo == 2'b10) begin

      if (sb_rco == 1'b1) begin //Check carry out
        sb_rco = 1'b0;
      end

      if (sb_Q > 4'b0010) begin //Check if add
        sb_Q[3:0] = sb_Q - 4'b0011;
      end
      else begin //Rebase
        if (sb_Q == 4'b0010) begin
          sb_Q = 4'b1111;
          sb_rco = 1'b1;
        end
        else if (sb_Q == 4'b0001) begin
          sb_Q = 4'b1110;
          sb_rco = 1'b1;
        end
        else begin
          sb_Q = 4'b1101;
          sb_rco = 1'b1;
        end

      end

    end
    if (modo == 2'b11) begin
      if (sb_rco == 1'b1) begin //Check carry out
        sb_rco = 1'b0;
      end

      sb_Q[3:0] = D;
      sb_rco = 1'b1;
    end

    // if (D == 4'b0000 && sb_state[1:0] != 2'b10) begin
    //   sb_state[1:0] = 2'b01;
    // end
    // else if (modo == 1'b1 && sb_state[1:0] != 2'b01) begin
    //   sb_state[1:0] = 2'b10;
    // end
    // else begin
    //   sb_state[1:0] = 2'b00;
    // end
  end
  else begin
    sb_Q[3:0] = 4'b0000;
    sb_rco = 1'b0;
  end
end

endmodule

tarea3/compare/compare_tb.v
`timescale 1ns/1ps
`include "scoreboard.v"
// Testbench Code Goes here


module compare_tb( enable, modo, D, rcoA, rcoB, rcoC, QA, QB, QC, clk);

input [3:0] QA;
input [3:0] QB;
input [3:0] QC;
output [3:0] D;
reg [3:0] D;
input clk;
input rcoA;
input rcoB;
input rcoC;
output [1:0] modo;
reg [1:0] modo;
output enable;
reg enable;

`include "driver.v"


integer log;
integer seed;


initial begin

  $dumpfile("output/gtkwave/comparison_verif.vcd");
  $dumpvars(0, RESULTS);

  assign seed = 400;


  drv_init();


  drv_random_request();
  drv_completely_random_request();
  drv_request();




  #200 $finish;
end


scoreboard sb(
.clk (clk),
.D (D),
.enable (enable),
.modo (modo)
);
endmodule

tarea3/clock.v
`timescale 1ns/1ps
module clk (clock);

output clock;
reg clock;

initial begin
clock = 0;
end

always begin
 #5 clock = !clock;
end

endmodule

tarea3/tb_top_compare.v
`timescale 1ns/1ps
`include "clock.v"
`include "compare/contadorA.v"
`include "compare/contadorB.v"
`include "compare/contadorC.v"
`include "compare/compare_tb.v"




module tb_top;
`include "compare/definitions.v"

clk clocks (.clock (clock));

compare_tb RESULTS(
.D (D),
.QA (QA),
.QB (QB),
.QC (QC),
.enable (enable),
.modo (modo),
.rcoA (rcoA),
.rcoB (rcoB),
.rcoC (rcoC),
.clk (clock)
);


countA dutA (
.D (D),
.Q (QA),
.enable (enable),
.modo (modo),
.rco (rcoA),
.clk (clock)
);


countB dutB (
.D (D),
.Q (QB),
.enable (enable),
.modo (modo),
.rco (rcoB),
.clk (clock)
);


countC dutC (
.D (D),
.Q (QC),
.enable (enable),
.modo (modo),
.rco (rcoC),
.clk (clock)
);



endmodule

tarea3/output/gtkwave/comparison_verif.vcd
$date
	Sun May 24 10:12:01 2020
$end
$version
	Icarus Verilog
$end
$timescale
	1ps
$end
$scope module tb_top $end
$scope module RESULTS $end
$var wire 1 ! rcoC $end
$var wire 1 " rcoB $end
$var wire 1 # rcoA $end
$var wire 1 $ clk $end
$var wire 4 % QC [3:0] $end
$var wire 4 & QB [3:0] $end
$var wire 4 ' QA [3:0] $end
$var reg 4 ( D [3:0] $end
$var reg 1 ) enable $end
$var reg 2 * modo [1:0] $end
$var integer 32 + seed [31:0] $end
$scope module sb $end
$var wire 4 , D [3:0] $end
$var wire 1 ) enable $end
$var wire 2 - modo [1:0] $end
$var wire 1 $ clk $end
$var reg 4 . sb_Q [3:0] $end
$var reg 1 / sb_rco $end
$upscope $end
$scope task drv_completely_random_request $end
$upscope $end
$scope task drv_init $end
$upscope $end
$scope task drv_random_request $end
$upscope $end
$scope task drv_request $end
$upscope $end
$upscope $end
$upscope $end
$enddefinitions $end
#0
$dumpvars
x/
bx .
bx -
bx ,
b110010000 +
bx *
x)
bx (
bx '
bx &
bx %
0$
x#
x"
x!
$end
#5000
0/
b0 .
1$
#10000
1)
b11 *
b11 -
b1111 (
b1111 ,
0$
#15000
0!
b1111 %
b1111 &
1#
b1111 '
b1111 .
1$
#20000
b0 *
b0 -
0$
#25000
b0 '
b0 &
1"
b0 %
1!
1/
b0 .
1$
#30000
0$
#35000
0!
b1 %
0"
b1 &
0#
b1 '
b1 .
0/
1$
#40000
b1 (
b1 ,
0)
0$
#45000
b0 '
b0 &
1"
b0 %
b0 .
1$
#50000
b11 (
b11 ,
1)
0$
#55000
b1 %
0"
b1 &
b1 '
b1 .
1$
#60000
b1101 (
b1101 ,
0$
#65000
b10 '
b10 &
1"
b10 %
b10 .
1$
#70000
b10 (
b10 ,
0$
#75000
b11 %
0"
b11 &
b11 '
b11 .
1$
#80000
b1101 (
b1101 ,
0$
#85000
b100 '
b100 &
b100 %
b100 .
1$
#90000
0)
0$
#95000
b0 %
1"
b0 &
b0 '
b0 .
1$
#100000
b1100 (
b1100 ,
1)
0$
#105000
b1 '
b1 &
0"
b1 %
b1 .
1$
#110000
b110 (
b110 ,
0$
#115000
b10 %
1"
b10 &
b10 '
b10 .
1$
#120000
b1010 (
b1010 ,
0$
#125000
b11 '
b11 &
0"
b11 %
b11 .
1$
#130000
b111 (
b111 ,
0$
#135000
b100 %
b100 &
b100 '
b100 .
1$
#140000
b1111 (
b1111 ,
0)
0$
#145000
b0 '
b0 &
1"
b0 %
b0 .
1$
#150000
b1110 (
b1110 ,
0$
#155000
1$
#160000
b101 (
b101 ,
0$
#165000
1$
#170000
b1101 (
b1101 ,
0$
#175000
1$
#180000
b101 (
b101 ,
1)
0$
#185000
b1 '
b1 &
0"
b1 %
b1 .
1$
#190000
b1010 (
b1010 ,
0$
#195000
b10 %
1"
b10 &
b10 '
b10 .
1$
#200000
b0 (
b0 ,
0)
0$
#205000
b0 '
b0 &
b0 %
b0 .
1$
#210000
b1101 (
b1101 ,
0$
#215000
1$
#220000
b11 (
b11 ,
0$
#225000
1$
#230000
1)
0$
#235000
b1 %
0"
b1 &
b1 '
b1 .
1$
#240000
b11 *
b11 -
0$
#245000
b11 '
1#
b11 &
1"
b11 %
b11 .
1$
#250000
b10 (
b10 ,
0$
#255000
b10 %
b10 &
b10 '
b10 .
1$
#260000
b1101 (
b1101 ,
0)
0$
#265000
b0 '
0#
b0 &
b0 %
b0 .
1$
#270000
b11 (
b11 ,
1)
0$
#275000
b11 %
b11 &
1#
b11 '
b11 .
1$
#280000
b1010 (
b1010 ,
0)
0$
#285000
b0 '
0#
b0 &
b0 %
b0 .
1$
#290000
b10 (
b10 ,
0$
#295000
1$
#300000
b1 (
b1 ,
0$
#305000
1$
#310000
b1000 (
b1000 ,
0$
#315000
1$
#320000
b1011 (
b1011 ,
1)
0$
#325000
b1011 '
1#
b1011 &
b1011 %
b1011 .
1$
#330000
b110 (
b110 ,
0)
0$
#335000
b0 %
b0 &
0#
b0 '
b0 .
1$
#340000
b10 *
b10 -
0$
#345000
1$
#350000
b1010 (
b1010 ,
0$
#355000
1$
#360000
b1 (
b1 ,
1)
0$
#365000
b1101 '
1#
b1101 &
b1101 %
1!
1/
b1101 .
1$
#370000
b1111 (
b1111 ,
0$
#375000
0!
b1010 %
0"
b1010 &
0#
b1010 '
b1010 .
0/
1$
#380000
b1010 (
b1010 ,
0$
#385000
b111 '
b111 &
b111 %
b111 .
1$
#390000
b101 (
b101 ,
0)
0$
#395000
b0 %
1"
b0 &
b0 '
b0 .
1$
#400000
b1001 (
b1001 ,
1)
0$
#405000
b1101 '
1#
b1101 &
b1101 %
1!
1/
b1101 .
1$
#410000
b1100 (
b1100 ,
0)
0$
#415000
0!
b0 %
b0 &
0#
b0 '
0/
b0 .
1$
#420000
b1111 (
b1111 ,
1)
0$
#425000
b1101 '
1#
b1101 &
b1101 %
1!
1/
b1101 .
1$
#430000
b111 (
b111 ,
0)
0$
#435000
0!
b0 %
b0 &
0#
b0 '
0/
b0 .
1$
#440000
b11 *
b11 -
0$
#445000
1$
#450000
b1011 (
b1011 ,
0$
#455000
1$
#460000
b1001 (
b1001 ,
1)
0$
#465000
b1001 '
1#
b1001 &
b1001 %
b1001 .
1$
#470000
b111 (
b111 ,
0)
0$
#475000
b0 %
b0 &
0#
b0 '
b0 .
1$
#480000
b110 (
b110 ,
1)
0$
#485000
b110 '
1#
b110 &
b110 %
b110 .
1$
#490000
b10 (
b10 ,
0)
0$
#495000
b0 %
b0 &
0#
b0 '
b0 .
1$
#500000
b111 (
b111 ,
0$
#505000
1$
#510000
b10 (
b10 ,
1)
0$
#515000
b10 %
b10 &
1#
b10 '
b10 .
1$
#520000
b1101 (
b1101 ,
0)
0$
#525000
b0 '
0#
b0 &
b0 %
b0 .
1$
#530000
b1111 (
b1111 ,
1)
0$
#535000
b1111 %
b1111 &
1#
b1111 '
b1111 .
1$
#540000
0$
#545000
1$
#550000
b1000 (
b1000 ,
0$
#555000
b1000 %
b1000 &
b1000 '
b1000 .
1$
#560000
b1001 (
b1001 ,
0$
#565000
b1001 '
b1001 &
b1001 %
b1001 .
1$
#570000
b1010 (
b1010 ,
0$
#575000
b1010 %
b1010 &
b1010 '
b1010 .
1$
#580000
b110 (
b110 ,
0)
0$
#585000
b0 '
0#
b0 &
b0 %
b0 .
1$
#590000
b1100 (
b1100 ,
0$
#595000
1$
#600000
b110 (
b110 ,
0$
#605000
1$
#610000
b11 (
b11 ,
1)
0$
#615000
b11 %
b11 &
1#
b11 '
b11 .
1$
#620000
0$
#625000
1$
#630000
b100 (
b100 ,
0$
#635000
b100 %
b100 &
b100 '
b100 .
1$
#640000
0$
#645000
0"
1$
#650000
b110 (
b110 ,
0$
#655000
b110 %
b110 &
b110 '
b110 .
1$
#660000
b1001 (
b1001 ,
0)
0$
#665000
b0 '
0#
b0 &
1"
b0 %
b0 .
1$
