tarea3/contadorA.v
/* Generated by Yosys 0.7 (git sha1 61f6811, gcc 6.2.0-11ubuntu1 -O2 -fdebug-prefix-map=/build/yosys-OIL3SR/yosys-0.7=. -fstack-protector-strong -fPIC -Os) */

module count(enable, clk, modo, D, rco, Q);
  wire [3:0] _000_;
  wire _001_;
  wire [31:0] _002_;
  wire [1:0] _003_;
  wire [1:0] _004_;
  wire [1:0] _005_;
  wire [1:0] _006_;
  wire [1:0] _007_;
  wire [1:0] _008_;
  wire [1:0] _009_;
  wire [1:0] _010_;
  wire [1:0] _011_;
  wire _012_;
  wire [1:0] _013_;
  wire _014_;
  wire [3:0] _015_;
  wire [3:0] _016_;
  wire [1:0] _017_;
  wire _018_;
  wire _019_;
  wire _020_;
  wire _021_;
  wire _022_;
  wire _023_;
  wire _024_;
  wire _025_;
  wire _026_;
  wire _027_;
  wire _028_;
  wire _029_;
  wire [3:0] _030_;
  wire _031_;
  wire _032_;
  wire _033_;
  wire _034_;
  wire _035_;
  wire [15:0] _036_;
  wire [3:0] _037_;
  wire [3:0] _038_;
  wire [31:0] _039_;
  wire [31:0] _040_;
  wire [31:0] _041_;
  wire _042_;
  wire [31:0] _043_;
  wire [31:0] _044_;
  wire _045_;
  wire _046_;
  wire _047_;
  input [3:0] D;
  output [3:0] Q;
  reg [3:0] Q;
  input clk;
  input enable;
  input [1:0] modo;
  output rco;
  reg rco;
  assign _003_[0] = _002_[0] | Q[1];
  assign _018_ = _003_[0] | _003_[1];
  assign _004_[0] = Q[0] | _015_[1];
  assign _003_[1] = Q[2] | Q[3];
  assign _019_ = _004_[0] | _003_[1];
  assign _005_[0] = _002_[0] | _015_[1];
  assign _005_[1] = _016_[2] | _016_[3];
  assign _020_ = _005_[0] | _005_[1];
  assign _021_ = _017_[0] | _017_[1];
  assign _022_ = modo[0] | _017_[1];
  assign _023_ = _017_[0] | modo[1];
  assign _006_[0] = _030_[0] | _030_[1];
  assign _006_[1] = _030_[2] | _030_[3];
  assign _031_ = _006_[0] | _006_[1];
  assign _042_ = _007_[0] | _007_[1];
  assign _008_[0] = _036_[2] | _036_[6];
  assign _008_[1] = _036_[10] | _036_[14];
  assign _037_[2] = _008_[0] | _008_[1];
  assign _009_[0] = _036_[3] | _036_[7];
  assign _009_[1] = _036_[11] | _036_[15];
  assign _037_[3] = _009_[0] | _009_[1];
  assign _010_[0] = _036_[1] | _036_[5];
  assign _010_[1] = _036_[9] | _036_[13];
  assign _037_[1] = _010_[0] | _010_[1];
  assign _011_[0] = _036_[0] | _036_[4];
  assign _011_[1] = _036_[8] | _036_[12];
  assign _037_[0] = _011_[0] | _011_[1];
  assign _007_[0] = _030_[0] | _033_;
  assign _007_[1] = _034_ | _035_;
  assign _012_ = modo[0] | modo[1];
  assign _013_[0] = Q[0] | Q[1];
  assign _014_ = _013_[0] | _003_[1];
  assign _027_ = ~_018_;
  assign _026_ = ~_019_;
  assign _024_ = ~_020_;
  assign _030_[0] = ~_021_;
  assign _033_ = ~_022_;
  assign _034_ = ~_023_;
  assign _035_ = ~_012_;
  assign _025_ = ~_014_;
  assign _028_ = _025_ | _027_;
  assign _029_ = _028_ | _026_;
  assign _001_ = enable ? _032_ : 1'b0;
  assign _000_[0] = enable ? _038_[0] : 1'b0;
  assign _000_[1] = enable ? _038_[1] : 1'b0;
  assign _000_[2] = enable ? _038_[2] : 1'b0;
  assign _000_[3] = enable ? _038_[3] : 1'b0;
  assign _032_ = _042_ ? _031_ : rco;
  assign _038_[0] = _042_ ? _037_[0] : Q[0];
  assign _038_[1] = _042_ ? _037_[1] : Q[1];
  assign _038_[2] = _042_ ? _037_[2] : Q[2];
  assign _038_[3] = _042_ ? _037_[3] : Q[3];
  always @(posedge clk)
      Q[0] <= _000_[0];
  always @(posedge clk)
      Q[1] <= _000_[1];
  always @(posedge clk)
      Q[2] <= _000_[2];
  always @(posedge clk)
      Q[3] <= _000_[3];
  always @(posedge clk)
      rco <= _001_;
  assign _045_ = _015_[1] & Q[0];
  assign _046_ = _016_[2] & _043_[1];
  assign _043_[1] = Q[1] | _045_;
  assign _043_[2] = Q[2] | _046_;
  assign _041_[1] = Q[1] & Q[0];
  assign _047_ = _016_[2] & _041_[1];
  assign _044_[2] = Q[2] | _047_;
  assign _041_[2] = Q[2] & _041_[1];
  assign _017_[1] = modo[1] ^ 1'b1;
  assign _017_[0] = modo[0] ^ 1'b1;
  assign _030_[3] = _024_ & _035_;
  assign _030_[2] = _025_ & _034_;
  assign _030_[1] = _029_ & _033_;
  assign _036_[12] = _002_[0] & _035_;
  assign _036_[13] = _002_[1] & _035_;
  assign _036_[14] = _002_[2] & _035_;
  assign _036_[15] = _002_[3] & _035_;
  assign _036_[8] = _002_[0] & _034_;
  assign _036_[9] = _039_[1] & _034_;
  assign _036_[10] = _039_[2] & _034_;
  assign _036_[11] = _039_[3] & _034_;
  assign _036_[4] = _002_[0] & _033_;
  assign _036_[5] = _002_[1] & _033_;
  assign _036_[6] = _040_[2] & _033_;
  assign _036_[7] = _040_[3] & _033_;
  assign _036_[0] = D[0] & _030_[0];
  assign _036_[1] = D[1] & _030_[0];
  assign _036_[2] = D[2] & _030_[0];
  assign _036_[3] = D[3] & _030_[0];
  assign _015_[1] = Q[1] ^ 1'b1;
  assign _016_[2] = Q[2] ^ 1'b1;
  assign _016_[3] = Q[3] ^ 1'b1;
  assign _002_[0] = Q[0] ^ 1'b1;
  assign _039_[1] = _015_[1] ^ Q[0];
  assign _039_[2] = _016_[2] ^ _043_[1];
  assign _039_[3] = _016_[3] ^ _043_[2];
  assign _040_[2] = _016_[2] ^ _041_[1];
  assign _040_[3] = _016_[3] ^ _044_[2];
  assign _002_[1] = Q[1] ^ Q[0];
  assign _002_[2] = Q[2] ^ _041_[1];
  assign _002_[3] = Q[3] ^ _041_[2];
endmodule

tarea3/checker.v

task checker;

repeat (200) @(negedge clk) begin
	if ({sb.sb_Q,sb.sb_rco} == {Q, rco}) begin
          $fdisplay(log, "PASS");
        end
        else begin
          $fdisplay(log, "Time=%.0f Error dut: Q=%b, rco=%b, scoreboard: Q=%b, rco=%b", $time, Q, rco, sb.sb_Q,sb.sb_rco);
        end
end
endtask

task random_checker;
repeat (10) @(negedge clk) begin
	if ({sb.sb_Q,sb.sb_rco} == {Q, rco}) begin
          $fdisplay(log, "PASS");
        end
        else begin
          $fdisplay(log, "Time=%.0f Error dut: Q=%b, rco=%b, scoreboard: Q=%b, rco=%b", $time, Q, rco, sb.sb_Q,sb.sb_rco);
        end
end
endtask

task completely_random_checker;
repeat (54) @(negedge clk) begin
	if ({sb.sb_Q,sb.sb_rco} == {Q, rco}) begin
          $fdisplay(log, "PASS");
        end
        else begin
          $fdisplay(log, "Time=%.0f Error dut: Q=%b, rco=%b, scoreboard: Q=%b, rco=%b", $time, Q, rco, sb.sb_Q,sb.sb_rco);
        end
end
endtask

tarea3/driver.v
//Init task for clean output signals
task drv_init;
  begin
    @(negedge clk) begin
      enable = 1;
      D = 4'b0000;
      modo = 2'b11;
    end
    @(negedge clk)
      enable = 1;
    @(negedge clk)
      enable = 1;
  end
endtask

//Drive request to the arbiter
task drv_request;
  begin

  input integer iteration;
  @(negedge clk) begin
    enable = $random;
    D = 4'b0000;
    modo = 2'b00;
  end
    repeat (iteration) begin
    @(negedge clk) begin
        D = 4'b0000;
    end
  end
endtask

tarea3/scoreboard.v
`timescale 1ns/1ps
//Scoreboard
module scoreboard (D, modo, enable, clk) ;

input [3:0] D;
input clk;
input enable;
input [1:0] modo;



//wire  sb_rco;
reg sb_rco;
reg [3:0] sb_Q;

//UPDATE THIS SECTION
always @(posedge clk)
begin
  if (enable == 1'b1) begin

    if (modo == 2'b00) begin//Check add 1

      if (sb_rco == 1'b1) begin //Check carry out
        sb_rco = 1'b0;
      end

      if (sb_Q < 4'b1111) begin //Check if add
        sb_Q[3:0] = sb_Q + 4'b0001;
      end
      else begin //Rebase
        sb_Q = 4'b0000;
        sb_rco = 1'b1;
      end
    end

    if (modo == 2'b01) begin //Check substract 1

      if (sb_rco == 1'b1) begin //Check carry out
        sb_rco = 1'b0;
      end

      if (sb_Q > 4'b0000) begin //Check if add
        sb_Q[3:0] = sb_Q - 4'b0001;
      end
      else begin //Rebase
        sb_Q = 4'b1111;
        sb_rco = 1'b1;
      end

    end
    if (modo == 2'b10) begin

      if (sb_rco == 1'b1) begin //Check carry out
        sb_rco = 1'b0;
      end

      if (sb_Q > 4'b0010) begin //Check if add
        sb_Q[3:0] = sb_Q - 4'b0011;
      end
      else begin //Rebase
        if (sb_Q == 4'b0010) begin
          sb_Q = 4'b1111;
          sb_rco = 1'b1;
        end
        else if (sb_Q == 4'b0001) begin
          sb_Q = 4'b1110;
          sb_rco = 1'b1;
        end
        else begin
          sb_Q = 4'b1101;
          sb_rco = 1'b1;
        end

      end

    end
    if (modo == 2'b11) begin
      if (sb_rco == 1'b1) begin //Check carry out
        sb_rco = 1'b0;
      end

      sb_Q[3:0] = D;
      sb_rco = 1'b1;
    end

    // if (D == 4'b0000 && sb_state[1:0] != 2'b10) begin
    //   sb_state[1:0] = 2'b01;
    // end
    // else if (modo == 1'b1 && sb_state[1:0] != 2'b01) begin
    //   sb_state[1:0] = 2'b10;
    // end
    // else begin
    //   sb_state[1:0] = 2'b00;
    // end
  end
  else begin
    sb_Q[3:0] = 4'b0000;
    sb_rco = 1'b0;
  end
end

endmodule

tarea3/contadorA_tb.v
`timescale 1ns/1ps
// Testbench Code Goes here
`include "scoreboard.v"

module contadorA_tb( enable, modo, D, rco, Q, clk);

input [3:0] Q;
output [3:0] D;
reg [3:0] D;
input clk;
input rco;
output [1:0] modo;
reg [1:0] modo;
output enable;
reg enable;

`include "driver.v"
`include "checker.v"

parameter ITERATIONS = 20;
integer log;

initial begin

  $dumpfile("contadorA_verif.vcd");
  $dumpvars(0);

  log = $fopen("tb.log");
  $fdisplay(log, "time=%5d, Simulation Start", $time);
  $fdisplay(log, "time=%5d, Starting Reset", $time);

  drv_init();

  $fdisplay(log, "time=%5d, Reset Completed", $time);

  $fdisplay(log, "time=%5d, Starting Test", $time);
  fork
    drv_request();
    checker();
  join
  $fdisplay(log, "time=%5d, Test Completed", $time);
  $fdisplay(log, "time=%5d, Simulation Completed", $time);
  $fclose(log);
  #200 $finish;
end

scoreboard sb(
.clk (clk),
.D (D),
.enable (enable),
.modo (modo)
);

endmodule

tarea3/clock.v
`timescale 1ns/1ps
module clk (clock);

output clock;
reg clock;

initial begin
clock = 0;
end

always begin
 #5 clock = !clock;
end

endmodule

tarea3/tb_topA.v
`include "clock.v"
`include "contadorA.v"
`include "contadorA_tb.v"

module tb_top;

clk clocks (.clock (clock));

contadorA_tb tb(
.D (D),
.Q (Q),
.enable (enable),
.modo (modo),
.rco (rco),
.clk (clock)
);

count dut (
.D (D),
.Q (Q),
.enable (enable),
.modo (modo),
.rco (rco),
.clk (clock)
);

endmodule

tarea3/output/gtkwave/contadorA_verif.vcd
$date
	Sun May 24 10:12:01 2020
$end
$version
	Icarus Verilog
$end
$timescale
	1ps
$end
$scope module tb_top $end
$var wire 1 ! rco $end
$var wire 2 " modo [1:0] $end
$var wire 1 # enable $end
$var wire 1 $ clock $end
$var wire 4 % Q [3:0] $end
$var wire 4 & D [3:0] $end
$scope module clocks $end
$var reg 1 $ clock $end
$upscope $end
$scope module dut $end
$var wire 1 ' _012_ $end
$var wire 1 ( _014_ $end
$var wire 1 ) _018_ $end
$var wire 1 * _019_ $end
$var wire 1 + _020_ $end
$var wire 1 , _021_ $end
$var wire 1 - _022_ $end
$var wire 1 . _023_ $end
$var wire 1 / _024_ $end
$var wire 1 0 _025_ $end
$var wire 1 1 _026_ $end
$var wire 1 2 _027_ $end
$var wire 1 3 _028_ $end
$var wire 1 4 _029_ $end
$var wire 1 5 _031_ $end
$var wire 1 6 _033_ $end
$var wire 1 7 _034_ $end
$var wire 1 8 _035_ $end
$var wire 1 9 _042_ $end
$var wire 1 : _045_ $end
$var wire 1 ; _046_ $end
$var wire 1 < _047_ $end
$var wire 1 $ clk $end
$var wire 2 = modo [1:0] $end
$var wire 1 # enable $end
$var wire 32 > _044_ [31:0] $end
$var wire 32 ? _043_ [31:0] $end
$var wire 32 @ _041_ [31:0] $end
$var wire 32 A _040_ [31:0] $end
$var wire 32 B _039_ [31:0] $end
$var wire 4 C _038_ [3:0] $end
$var wire 4 D _037_ [3:0] $end
$var wire 16 E _036_ [15:0] $end
$var wire 1 F _032_ $end
$var wire 4 G _030_ [3:0] $end
$var wire 2 H _017_ [1:0] $end
$var wire 4 I _016_ [3:0] $end
$var wire 4 J _015_ [3:0] $end
$var wire 2 K _013_ [1:0] $end
$var wire 2 L _011_ [1:0] $end
$var wire 2 M _010_ [1:0] $end
$var wire 2 N _009_ [1:0] $end
$var wire 2 O _008_ [1:0] $end
$var wire 2 P _007_ [1:0] $end
$var wire 2 Q _006_ [1:0] $end
$var wire 2 R _005_ [1:0] $end
$var wire 2 S _004_ [1:0] $end
$var wire 2 T _003_ [1:0] $end
$var wire 32 U _002_ [31:0] $end
$var wire 1 V _001_ $end
$var wire 4 W _000_ [3:0] $end
$var wire 4 X D [3:0] $end
$var reg 4 Y Q [3:0] $end
$var reg 1 ! rco $end
$upscope $end
$scope module tb $end
$var wire 4 Z Q [3:0] $end
$var wire 1 $ clk $end
$var wire 1 ! rco $end
$var reg 4 [ D [3:0] $end
$var reg 1 # enable $end
$var reg 2 \ modo [1:0] $end
$var integer 32 ] log [31:0] $end
$scope module sb $end
$var wire 4 ^ D [3:0] $end
$var wire 1 $ clk $end
$var wire 1 # enable $end
$var wire 2 _ modo [1:0] $end
$var reg 4 ` sb_Q [3:0] $end
$var reg 1 a sb_rco $end
$upscope $end
$scope task checker $end
$upscope $end
$scope task completely_random_checker $end
$upscope $end
$scope task drv_completely_random_request $end
$upscope $end
$scope task drv_init $end
$upscope $end
$scope task drv_random_request $end
$upscope $end
$scope task drv_request $end
$upscope $end
$scope task random_checker $end
$upscope $end
$upscope $end
$upscope $end
$enddefinitions $end
#0
$dumpvars
xa
bx `
bx _
bx ^
b10 ]
bx \
bx [
bx Z
bx Y
bx X
bx W
xV
bzxxxx U
bx T
bzx S
bx R
bx Q
bx P
bx O
bx N
bx M
bx L
bzx K
bzxz J
bxzz I
bx H
bx G
xF
bx E
bx D
bx C
bzxxxz B
bzxxzz A
bzxxz @
bzxxz ?
bzxzz >
bx =
x<
x;
x:
x9
x8
x7
x6
x5
x4
x3
x2
x1
x0
x/
x.
x-
x,
x+
x*
x)
x(
x'
bx &
bx %
0$
x#
bx "
x!
$end
#5000
0a
b0 `
1$
#10000
b1111 W
1V
1#
b1111 C
b1111 D
1F
19
15
b1 Q
b1 L
b1 M
b1 O
b1 N
0,
b1 P
b1 G
b1111 E
08
07
06
b0 H
1'
1.
1-
b11 "
b11 =
b11 \
b11 _
b1111 &
b1111 X
b1111 [
b1111 ^
0$
#15000
1/
04
03
0+
02
01
00
1)
0;
bz111z B
0:
1*
1(
bz11zz A
0<
b0 R
bz1zz >
b0zz I
b11 T
bz11z ?
bz0z J
bz1 S
bz1 K
bz11z @
bz0000 U
1!
b1111 %
b1111 Y
b1111 Z
b1111 `
1$
#20000
b0 W
b0 C
b0 D
b0 L
b10 Q
b0 M
b0 O
b0 N
1,
b1000 G
b10 P
b0 E
18
07
06
b11 H
0'
1.
1-
b0 "
b0 =
b0 \
b0 _
0$
#25000
0V
0F
05
b1 W
b0 Q
b1 C
b0 G
b1 D
0/
b10 L
b0 O
14
13
1+
b0 N
01
10
02
1*
0(
1)
b11 R
b1000000000000 E
bz1 S
bz111z B
bz0 K
bz1z J
bz00z ?
bz0zz >
bz00z @
b1 T
b11zz I
bz0001 U
b0 %
b0 Y
b0 Z
1a
b0 `
1$
#30000
0$
#35000
b10 W
b10 C
b10 D
14
12
13
b0 L
0)
b10 M
00
1;
1(
b0 T
b10000000000000 E
bz11z ?
bz1 K
1:
bz000z B
bz0010 U
0!
b1 %
b1 Y
b1 Z
b1 `
0a
1$
#40000
b0 W
b1 &
b1 X
b1 [
b1 ^
0#
0$
#45000
b1 C
b1 D
02
b10 L
1)
b0 M
10
0;
0(
b1 T
b1000000000000 E
bz00z ?
bz0 K
0:
bz111z B
bz0001 U
b0 %
b0 Y
b0 Z
b0 `
1$
#50000
b1 W
b11 &
b11 X
b11 [
b11 ^
1#
0$
#55000
b10 W
b10 C
b10 D
14
12
13
b0 L
0)
b10 M
00
1;
1(
b0 T
b10000000000000 E
bz11z ?
bz1 K
1:
bz000z B
bz0010 U
b1 %
b1 Y
b1 Z
b1 `
1$
#60000
b1101 &
b1101 X
b1101 [
b1101 ^
0$
#65000
b11 W
b11 C
b11 D
11
b10 L
03
0*
02
b11000000000000 E
1)
bz0 S
0:
bz0011 U
bz000z B
b1 T
bz0z J
b10 %
b10 Y
b10 Z
b10 `
1$
#70000
b10 &
b10 X
b10 [
b10 ^
0$
#75000
b100 W
b100 C
b10 O
b100 D
04
b0 L
b0 M
01
bz1zz >
1*
bz00zz A
1<
b10 R
b100000000000000 E
bz1 S
bz01z @
bz001z B
bz0100 U
b11 %
b11 Y
b11 Z
b11 `
1$
#80000
b1101 &
b1101 X
b1101 [
b1101 ^
0$
#85000
b101 W
b101 C
b0 N
b101 D
b10 L
b10 O
b11 R
0<
0;
b101000000000000 E
bz1 S
bz001z B
bz0 K
bz10z ?
bz1z J
b11 T
bz00z @
b10zz I
bz0101 U
b100 %
b100 Y
b100 Z
b100 `
1$
#90000
b0 W
0#
0$
#95000
b1 C
b1 D
14
13
b0 O
10
0(
bz11zz A
bz111z B
b1000000000000 E
b1 T
bz00z ?
bz0zz >
b11zz I
bz0001 U
b0 %
b0 Y
b0 Z
b0 `
1$
#100000
b1 W
b1100 &
b1100 X
b1100 [
b1100 ^
1#
0$
#105000
b10 W
b10 C
b10 D
14
12
13
b0 L
0)
b10 M
00
1;
1(
b0 T
b10000000000000 E
bz11z ?
bz1 K
1:
bz000z B
bz0010 U
b1 %
b1 Y
b1 Z
b1 `
1$
#110000
b110 &
b110 X
b110 [
b110 ^
0$
#115000
b11 W
b11 C
b11 D
11
03
0*
b10 L
02
1)
bz0 S
b11000000000000 E
b1 T
bz0z J
0:
bz0011 U
bz000z B
b10 %
b10 Y
b10 Z
b10 `
1$
#120000
b1010 &
b1010 X
b1010 [
b1010 ^
0$
#125000
b100 W
b100 C
b10 O
b100 D
04
b0 L
b0 M
01
bz1zz >
1*
bz00zz A
1<
b10 R
b100000000000000 E
bz1 S
bz01z @
bz001z B
bz0100 U
b11 %
b11 Y
b11 Z
b11 `
1$
#130000
b111 &
b111 X
b111 [
b111 ^
0$
#135000
b101 W
b101 C
b0 N
b101 D
b10 O
b10 L
0;
0<
b101000000000000 E
b11 R
b10zz I
b11 T
bz10z ?
bz1z J
bz1 S
bz0 K
bz00z @
bz0101 U
bz001z B
b100 %
b100 Y
b100 Z
b100 `
1$
#140000
b0 W
b1111 &
b1111 X
b1111 [
b1111 ^
0#
0$
#145000
b1 C
b1 D
14
13
b0 O
10
0(
bz11zz A
bz111z B
b1000000000000 E
b1 T
bz00z ?
bz0zz >
b11zz I
bz0001 U
b0 %
b0 Y
b0 Z
b0 `
1$
#150000
b1110 &
b1110 X
b1110 [
b1110 ^
0$
#155000
1$
#160000
b101 &
b101 X
b101 [
b101 ^
0$
#165000
1$
#170000
b1101 &
b1101 X
b1101 [
b1101 ^
0$
#175000
1$
#180000
b1 W
b101 &
b101 X
b101 [
b101 ^
1#
0$
#185000
b10 W
b10 C
b10 D
14
12
13
b0 L
0)
b10 M
00
1;
1(
b0 T
b10000000000000 E
bz11z ?
bz1 K
1:
bz000z B
bz0010 U
b1 %
b1 Y
b1 Z
b1 `
1$
#190000
b1010 &
b1010 X
b1010 [
b1010 ^
0$
#195000
b11 W
b11 C
b11 D
11
03
0*
b10 L
02
1)
bz0 S
b11000000000000 E
b1 T
bz0z J
0:
bz0011 U
bz000z B
b10 %
b10 Y
b10 Z
b10 `
1$
#200000
b0 W
b0 &
b0 X
b0 [
b0 ^
0#
0$
#205000
b1 C
b1 D
01
13
1*
b0 M
10
0(
0;
bz111z B
bz1 S
b1000000000000 E
bz0 K
bz00z ?
bz1z J
bz0001 U
b0 %
b0 Y
b0 Z
b0 `
1$
#210000
b1101 &
b1101 X
b1101 [
b1101 ^
0$
#215000
1$
#220000
b11 &
b11 X
b11 [
b11 ^
0$
#225000
1$
#230000
b1 W
1#
0$
#235000
b10 W
b10 C
b10 D
14
12
13
b0 L
0)
b10 M
00
1;
1(
b0 T
b10000000000000 E
bz11z ?
bz1 K
1:
bz000z B
bz0010 U
b1 %
b1 Y
b1 Z
b1 `
1$
#240000
1V
1F
b1 L
15
b11 W
b11 D
b1 Q
b11 C
b1 M
19
b1 G
0,
b11 E
b1 P
08
b0 H
1'
b11 "
b11 =
b11 \
b11 _
0$
#245000
04
03
02
bz1zz >
1)
bz00zz A
1<
bz001z B
0:
b10 R
b1 T
bz01z @
bz0z J
bz0100 U
b11 %
b11 Y
b11 Z
1!
b11 `
1$
#250000
b10 W
b10 C
b10 D
b0 L
b10 E
b10 &
b10 X
b10 [
b10 ^
0$
#255000
14
11
bz0zz >
0*
bz11zz A
0<
b11 R
bz0 S
bz00z @
bz000z B
bz0011 U
b10 %
b10 Y
b10 Z
b10 `
1$
#260000
b1101 C
b1101 D
b1 N
b1 O
b0 M
b1 L
b1101 E
b0 W
0V
b1101 &
b1101 X
b1101 [
b1101 ^
0#
0$
#265000
01
13
1*
10
0(
0;
bz111z B
bz1 S
bz0 K
bz00z ?
bz1z J
bz0001 U
b0 %
b0 Y
b0 Z
0!
b0 `
1$
#270000
b11 C
b11 D
b0 N
b0 O
b1 M
b11 E
b11 W
1V
b11 &
b11 X
b11 [
b11 ^
1#
0$
#275000
04
03
00
bz1zz >
1;
1(
bz00zz A
1<
b10 R
bz11z ?
bz0z J
bz1 K
0:
bz01z @
bz0100 U
bz001z B
1!
b11 %
b11 Y
b11 Z
b11 `
1$
#280000
b1010 C
b1010 D
b1 N
b0 L
b1010 E
b0 W
0V
b1010 &
b1010 X
b1010 [
b1010 ^
0#
0$
#285000
14
13
01
02
10
bz0zz >
1*
1)
0(
0;
bz11zz A
0<
b11 R
bz1 S
bz0001 U
bz111z B
b1 T
bz0 K
bz00z ?
bz00z @
bz1z J
b0 %
b0 Y
b0 Z
0!
b0 `
1$
#290000
b10 C
b10 D
b0 N
b10 E
b10 &
b10 X
b10 [
b10 ^
0$
#295000
1$
#300000
b1 C
b1 D
b0 M
b1 L
b1 E
b1 &
b1 X
b1 [
b1 ^
0$
#305000
1$
#310000
b1000 C
b1000 D
b1 N
b0 L
b1000 E
b1000 &
b1000 X
b1000 [
b1000 ^
0$
#315000
1$
#320000
b1011 C
b1011 D
b1 M
b1 L
b1011 E
b1011 W
1V
b1011 &
b1011 X
b1011 [
b1011 ^
1#
0$
#325000
04
03
bz1zz >
00
1;
1<
b10 R
1(
bz10zz A
0:
bz101z B
bz1 K
bz11z ?
bz01z @
bz0z J
b11 T
b1zz I
bz1100 U
b1011 %
b1011 Y
b1011 Z
1!
b1011 `
1$
#330000
b110 C
b110 D
b0 N
b1 O
b0 L
b110 E
b0 W
0V
b110 &
b110 X
b110 [
b110 ^
0#
0$
#335000
14
13
02
01
10
bz0zz >
1)
0;
1*
0(
bz11zz A
0<
b11 R
b11zz I
b1 T
bz00z ?
bz1z J
bz1 S
bz0 K
bz00z @
bz0001 U
bz111z B
0!
b0 %
b0 Y
b0 Z
b0 `
1$
#340000
b1101 C
b0 M
b1101 D
b1 L
b1 N
1,
b10 G
b11010000 E
16
b1 H
0-
b10 "
b10 =
b10 \
b10 _
0$
#345000
1$
#350000
b1010 &
b1010 X
b1010 [
b1010 ^
0$
#355000
1$
#360000
b1101 W
1V
b1 &
b1 X
b1 [
b1 ^
1#
0$
#365000
0V
0F
b1010 W
05
b1010 C
b0 Q
b1010 D
b0 O
b0 G
04
b0 L
b1 M
03
00
b10100000 E
bz10zz A
1(
b1 R
bz1 K
1:
bz110z B
bz11z ?
bz1zz >
b10 T
b0zz I
bz1110 U
b1101 %
b1101 Y
b1101 Z
1!
1a
b1101 `
1$
#370000
b1111 &
b1111 X
b1111 [
b1111 ^
0$
#375000
b111 W
b111 C
b0 N
b1 O
b111 D
b1 L
bz01zz A
1;
b11 R
bz0 S
b1110000 E
bz11z ?
bz0zz >
b1zz I
b11 T
bz0z J
0:
bz1011 U
bz100z B
0!
b1010 %
b1010 Y
b1010 Z
b1010 `
0a
1$
#380000
b1010 &
b1010 X
b1010 [
b1010 ^
0$
#385000
b100 W
b100 C
b100 D
b0 L
b0 M
b10 R
b1000000 E
0;
bz1 S
bz11z @
bz011z B
bz1zz >
b10zz I
bz1000 U
b111 %
b111 Y
b111 Z
b111 `
1$
#390000
b0 W
b101 &
b101 X
b101 [
b101 ^
0#
0$
#395000
1F
15
b1101 C
b1 Q
b1 N
b1101 D
b10 G
14
13
b1 L
02
01
10
bz11zz A
1)
1*
0(
b11010000 E
b11 R
bz0zz >
b11zz I
b1 T
bz00z ?
bz1z J
bz1 S
bz0 K
bz00z @
bz0001 U
bz111z B
b0 %
b0 Y
b0 Z
b0 `
1$
#400000
b1101 W
1V
b1001 &
b1001 X
b1001 [
b1001 ^
1#
0$
#405000
0V
0F
b1010 W
05
b1010 C
b0 Q
b1010 D
b0 O
b0 G
04
b0 L
b1 M
03
00
b10100000 E
bz10zz A
1(
b1 R
bz1 K
1:
bz110z B
bz11z ?
bz1zz >
b10 T
b0zz I
bz1110 U
b1101 %
b1101 Y
b1101 Z
1!
1a
b1101 `
1$
#410000
b0 W
b1100 &
b1100 X
b1100 [
b1100 ^
0#
0$
#415000
1F
15
b1 Q
b1101 C
b1 O
b10 G
b1101 D
14
13
b1 L
b0 M
02
10
1)
bz11zz A
b11 R
0(
b11010000 E
b1 T
bz00z ?
bz0zz >
b11zz I
bz0 K
0:
bz111z B
bz0001 U
0!
b0 %
b0 Y
b0 Z
0a
b0 `
1$
#420000
b1101 W
1V
b1111 &
b1111 X
b1111 [
b1111 ^
1#
0$
#425000
0V
0F
b1010 W
05
b1010 C
b0 Q
b1010 D
b0 O
b0 G
04
b0 L
b1 M
03
00
b10100000 E
bz10zz A
1(
b1 R
bz1 K
1:
bz110z B
bz11z ?
bz1zz >
b10 T
b0zz I
bz1110 U
b1101 %
b1101 Y
b1101 Z
1!
1a
b1101 `
1$
#430000
b0 W
b111 &
b111 X
b111 [
b111 ^
0#
0$
#435000
1F
15
b1 Q
b1101 C
b1 O
b10 G
b1101 D
14
13
b1 L
b0 M
02
10
1)
bz11zz A
b11 R
0(
b11010000 E
b1 T
bz00z ?
bz0zz >
b11zz I
bz0 K
0:
bz111z B
bz0001 U
0!
b0 %
b0 Y
b0 Z
0a
b0 `
1$
#440000
b1 M
15
b111 D
1F
b111 C
b1 Q
b1 L
b1 O
b0 N
19
0,
b1 G
b111 E
b1 P
06
b0 H
1-
b11 "
b11 =
b11 \
b11 _
0$
#445000
1$
#450000
b1011 C
b1011 D
b1 N
b0 O
b1011 E
b1011 &
b1011 X
b1011 [
b1011 ^
0$
#455000
1$
#460000
b1001 C
b1001 D
b0 M
b1001 E
b1001 W
1V
b1001 &
b1001 X
b1001 [
b1001 ^
1#
0$
#465000
04
03
1;
00
1(
bz01zz A
bz11z ?
bz1 K
1:
bz100z B
b10 T
b1zz I
bz1010 U
b1001 %
b1001 Y
b1001 Z
1!
b1001 `
1$
#470000
b111 C
b111 D
b0 N
b1 O
b1 M
b111 E
b0 W
0V
b111 &
b111 X
b111 [
b111 ^
0#
0$
#475000
14
13
02
10
0;
1)
bz11zz A
0(
bz00z ?
b1 T
b11zz I
bz0 K
0:
bz111z B
bz0001 U
0!
b0 %
b0 Y
b0 Z
b0 `
1$
#480000
b110 C
b110 D
b0 L
b110 E
b110 W
1V
b110 &
b110 X
b110 [
b110 ^
1#
0$
#485000
04
03
00
bz0 S
1(
bz010z B
bz00zz A
bz1 K
bz0z J
b11 T
bz11z ?
bz1zz >
b10zz I
bz0111 U
b110 %
b110 Y
b110 Z
1!
b110 `
1$
#490000
b10 C
b10 D
b0 O
b10 E
b0 W
0V
b10 &
b10 X
b10 [
b10 ^
0#
0$
#495000
14
13
01
10
1*
bz11zz A
0(
bz111z B
bz1 S
b1 T
bz0zz >
b11zz I
bz0 K
bz00z ?
bz1z J
bz0001 U
0!
b0 %
b0 Y
b0 Z
b0 `
1$
#500000
b111 C
b111 D
b1 O
b1 L
b111 E
b111 &
b111 X
b111 [
b111 ^
0$
#505000
1$
#510000
b10 C
b10 D
b0 O
b0 L
b10 E
b10 W
1V
b10 &
b10 X
b10 [
b10 ^
1#
0$
#515000
11
03
0*
00
1(
1;
bz000z B
bz0 S
bz1 K
bz11z ?
bz0z J
bz0011 U
1!
b10 %
b10 Y
b10 Z
b10 `
1$
#520000
b1101 C
b1101 D
b1 N
b1 O
b0 M
b1 L
b1101 E
b0 W
0V
b1101 &
b1101 X
b1101 [
b1101 ^
0#
0$
#525000
01
13
1*
10
0(
0;
bz111z B
bz1 S
bz0 K
bz00z ?
bz1z J
bz0001 U
b0 %
b0 Y
b0 Z
0!
b0 `
1$
#530000
b1111 C
b1111 D
b1 M
b1111 E
b1111 W
1V
b1111 &
b1111 X
b1111 [
b1111 ^
1#
0$
#535000
04
1/
03
0+
00
1(
b0 R
b11 T
bz1zz >
b0zz I
bz11z ?
bz0z J
bz1 K
0:
bz11z @
bz0000 U
bz111z B
1!
b1111 %
b1111 Y
b1111 Z
b1111 `
1$
#540000
0$
#545000
1$
