tarea3/contadorA.v
/* Generated by Yosys 0.7 (git sha1 61f6811, gcc 6.2.0-11ubuntu1 -O2 -fdebug-prefix-map=/build/yosys-OIL3SR/yosys-0.7=. -fstack-protector-strong -fPIC -Os) */

module count(enable, clk, modo, D, rco, Q);
  wire [3:0] _000_;
  wire _001_;
  wire [31:0] _002_;
  wire [1:0] _003_;
  wire [1:0] _004_;
  wire [1:0] _005_;
  wire [1:0] _006_;
  wire [1:0] _007_;
  wire [1:0] _008_;
  wire [1:0] _009_;
  wire [1:0] _010_;
  wire [1:0] _011_;
  wire _012_;
  wire [1:0] _013_;
  wire _014_;
  wire [3:0] _015_;
  wire [3:0] _016_;
  wire [1:0] _017_;
  wire _018_;
  wire _019_;
  wire _020_;
  wire _021_;
  wire _022_;
  wire _023_;
  wire _024_;
  wire _025_;
  wire _026_;
  wire _027_;
  wire _028_;
  wire _029_;
  wire [3:0] _030_;
  wire _031_;
  wire _032_;
  wire _033_;
  wire _034_;
  wire _035_;
  wire [15:0] _036_;
  wire [3:0] _037_;
  wire [3:0] _038_;
  wire [31:0] _039_;
  wire [31:0] _040_;
  wire [31:0] _041_;
  wire _042_;
  wire [31:0] _043_;
  wire [31:0] _044_;
  wire _045_;
  wire _046_;
  wire _047_;
  input [3:0] D;
  output [3:0] Q;
  reg [3:0] Q;
  input clk;
  input enable;
  input [1:0] modo;
  output rco;
  reg rco;
  assign _003_[0] = _002_[0] | Q[1];
  assign _018_ = _003_[0] | _003_[1];
  assign _004_[0] = Q[0] | _015_[1];
  assign _003_[1] = Q[2] | Q[3];
  assign _019_ = _004_[0] | _003_[1];
  assign _005_[0] = _002_[0] | _015_[1];
  assign _005_[1] = _016_[2] | _016_[3];
  assign _020_ = _005_[0] | _005_[1];
  assign _021_ = _017_[0] | _017_[1];
  assign _022_ = modo[0] | _017_[1];
  assign _023_ = _017_[0] | modo[1];
  assign _006_[0] = _030_[0] | _030_[1];
  assign _006_[1] = _030_[2] | _030_[3];
  assign _031_ = _006_[0] | _006_[1];
  assign _042_ = _007_[0] | _007_[1];
  assign _008_[0] = _036_[2] | _036_[6];
  assign _008_[1] = _036_[10] | _036_[14];
  assign _037_[2] = _008_[0] | _008_[1];
  assign _009_[0] = _036_[3] | _036_[7];
  assign _009_[1] = _036_[11] | _036_[15];
  assign _037_[3] = _009_[0] | _009_[1];
  assign _010_[0] = _036_[1] | _036_[5];
  assign _010_[1] = _036_[9] | _036_[13];
  assign _037_[1] = _010_[0] | _010_[1];
  assign _011_[0] = _036_[0] | _036_[4];
  assign _011_[1] = _036_[8] | _036_[12];
  assign _037_[0] = _011_[0] | _011_[1];
  assign _007_[0] = _030_[0] | _033_;
  assign _007_[1] = _034_ | _035_;
  assign _012_ = modo[0] | modo[1];
  assign _013_[0] = Q[0] | Q[1];
  assign _014_ = _013_[0] | _003_[1];
  assign _027_ = ~_018_;
  assign _026_ = ~_019_;
  assign _024_ = ~_020_;
  assign _030_[0] = ~_021_;
  assign _033_ = ~_022_;
  assign _034_ = ~_023_;
  assign _035_ = ~_012_;
  assign _025_ = ~_014_;
  assign _028_ = _025_ | _027_;
  assign _029_ = _028_ | _026_;
  assign _001_ = enable ? _032_ : 1'b0;
  assign _000_[0] = enable ? _038_[0] : 1'b0;
  assign _000_[1] = enable ? _038_[1] : 1'b0;
  assign _000_[2] = enable ? _038_[2] : 1'b0;
  assign _000_[3] = enable ? _038_[3] : 1'b0;
  assign _032_ = _042_ ? _031_ : rco;
  assign _038_[0] = _042_ ? _037_[0] : Q[0];
  assign _038_[1] = _042_ ? _037_[1] : Q[1];
  assign _038_[2] = _042_ ? _037_[2] : Q[2];
  assign _038_[3] = _042_ ? _037_[3] : Q[3];
  always @(posedge clk)
      Q[0] <= _000_[0];
  always @(posedge clk)
      Q[1] <= _000_[1];
  always @(posedge clk)
      Q[2] <= _000_[2];
  always @(posedge clk)
      Q[3] <= _000_[3];
  always @(posedge clk)
      rco <= _001_;
  assign _045_ = _015_[1] & Q[0];
  assign _046_ = _016_[2] & _043_[1];
  assign _043_[1] = Q[1] | _045_;
  assign _043_[2] = Q[2] | _046_;
  assign _041_[1] = Q[1] & Q[0];
  assign _047_ = _016_[2] & _041_[1];
  assign _044_[2] = Q[2] | _047_;
  assign _041_[2] = Q[2] & _041_[1];
  assign _017_[1] = modo[1] ^ 1'b1;
  assign _017_[0] = modo[0] ^ 1'b1;
  assign _030_[3] = _024_ & _035_;
  assign _030_[2] = _025_ & _034_;
  assign _030_[1] = _029_ & _033_;
  assign _036_[12] = _002_[0] & _035_;
  assign _036_[13] = _002_[1] & _035_;
  assign _036_[14] = _002_[2] & _035_;
  assign _036_[15] = _002_[3] & _035_;
  assign _036_[8] = _002_[0] & _034_;
  assign _036_[9] = _039_[1] & _034_;
  assign _036_[10] = _039_[2] & _034_;
  assign _036_[11] = _039_[3] & _034_;
  assign _036_[4] = _002_[0] & _033_;
  assign _036_[5] = _002_[1] & _033_;
  assign _036_[6] = _040_[2] & _033_;
  assign _036_[7] = _040_[3] & _033_;
  assign _036_[0] = D[0] & _030_[0];
  assign _036_[1] = D[1] & _030_[0];
  assign _036_[2] = D[2] & _030_[0];
  assign _036_[3] = D[3] & _030_[0];
  assign _015_[1] = Q[1] ^ 1'b1;
  assign _016_[2] = Q[2] ^ 1'b1;
  assign _016_[3] = Q[3] ^ 1'b1;
  assign _002_[0] = Q[0] ^ 1'b1;
  assign _039_[1] = _015_[1] ^ Q[0];
  assign _039_[2] = _016_[2] ^ _043_[1];
  assign _039_[3] = _016_[3] ^ _043_[2];
  assign _040_[2] = _016_[2] ^ _041_[1];
  assign _040_[3] = _016_[3] ^ _044_[2];
  assign _002_[1] = Q[1] ^ Q[0];
  assign _002_[2] = Q[2] ^ _041_[1];
  assign _002_[3] = Q[3] ^ _041_[2];
endmodule

tarea3/checker.v

task checker;

repeat (60) @(negedge clk) begin
	if ({sb.sb_Q,sb.sb_rco} == {Q, rco}) begin
          $fdisplay(log, "PASS");
        end
        else begin
          $fdisplay(log, "Time=%.0f Error dut: Q=%b, rco=%b, scoreboard: Q=%b, rco=%b", $time, Q, rco, sb.sb_Q,sb.sb_rco);
        end
end
endtask

tarea3/driver.v
//Init task for clean output signals
task drv_init;
  begin
    @(negedge clk) begin
      enable <= 1'b1;
      D = 4'b1111;
      modo = 2'b11;
    end
    @(negedge clk) begin
      enable = 1;
      modo = 2'b00;
    end
    @(negedge clk)
      enable = 1;
  end
endtask

//Drive request to the arbiter
task drv_request;
begin
@(negedge clk);
enable <= 1'b1;
D = 4'b0000;
modo = 2'b00;
#160 @(negedge clk);
modo = 2'b01;
#160 @(negedge clk);
modo = 2'b10;
#20 @(negedge clk);

end
endtask

/*
@(negedge clk) begin
  enable <= 1'b1;
  D = 4'b0000;
  modo = 2'b00;
  repeat (8) begin
    @(negedge clk)begin
      enable = 1;
    end
  end
  @(negedge clk)begin
    modo = 2'b01;
  end
  repeat (1) begin
  @(negedge clk)begin
    enable = 1;
  end
  end

  modo = 2'b10;
  repeat (8) begin
    @(negedge clk)begin
      enable = 1;
    end
  end



end
*/



/*
repeat (8) begin
  D = 4'b0000;
end
*/

tarea3/scoreboard.v
`timescale 1ns/1ps
//Scoreboard
module scoreboard (D, modo, enable, clk) ;

input [3:0] D;
input clk;
input enable;
input [1:0] modo;



//wire  sb_rco;
reg sb_rco;
reg [3:0] sb_Q;

//UPDATE THIS SECTION
always @(posedge clk)
begin
  if (enable == 1'b1) begin

    if (modo == 2'b00) begin//Check add 1

      if (sb_rco == 1'b1) begin //Check carry out
        sb_rco = 1'b0;
      end

      if (sb_Q < 4'b1111) begin //Check if add
        sb_Q[3:0] = sb_Q + 4'b0001;
      end
      else begin //Rebase
        sb_Q = 4'b0000;
        sb_rco = 1'b1;
      end
    end

    if (modo == 2'b01) begin //Check substract 1

      if (sb_rco == 1'b1) begin //Check carry out
        sb_rco = 1'b0;
      end

      if (sb_Q > 4'b0000) begin //Check if add
        sb_Q[3:0] = sb_Q - 4'b0001;
      end
      else begin //Rebase
        sb_Q = 4'b1111;
        sb_rco = 1'b1;
      end

    end
    if (modo == 2'b10) begin

      if (sb_rco == 1'b1) begin //Check carry out
        sb_rco = 1'b0;
      end

      if (sb_Q > 4'b0010) begin //Check if add
        sb_Q[3:0] = sb_Q - 4'b0011;
      end
      else begin //Rebase
        if (sb_Q == 4'b0010) begin
          sb_Q = 4'b1111;
          sb_rco = 1'b1;
        end
        else if (sb_Q == 4'b0001) begin
          sb_Q = 4'b1110;
          sb_rco = 1'b1;
        end
        else begin
          sb_Q = 4'b1101;
          sb_rco = 1'b1;
        end

      end

    end
    if (modo == 2'b11) begin
      if (sb_rco == 1'b1) begin //Check carry out
        sb_rco = 1'b0;
      end

      sb_Q[3:0] = D;
      sb_rco = 1'b0;
    end

    // if (D == 4'b0000 && sb_state[1:0] != 2'b10) begin
    //   sb_state[1:0] = 2'b01;
    // end
    // else if (modo == 1'b1 && sb_state[1:0] != 2'b01) begin
    //   sb_state[1:0] = 2'b10;
    // end
    // else begin
    //   sb_state[1:0] = 2'b00;
    // end
  end

end

endmodule

tarea3/contadorA_tb.v
`timescale 1ns/1ps
// Testbench Code Goes here
`include "scoreboard.v"

module contadorA_tb( enable, modo, D, rco, Q, clk);

input [3:0] Q;
output [3:0] D;
reg [3:0] D;
input clk;
input rco;
output [1:0] modo;
reg [1:0] modo;
output enable;
reg enable;

`include "driver.v"
`include "checker.v"


integer log;

initial begin

  $dumpfile("output/gtkwave/contadorA_verif.vcd");
  $dumpvars(0);

  log = $fopen("output/logs/tbA.log");
  $fdisplay(log, "time=%5d, Simulation Start", $time);
  $fdisplay(log, "time=%5d, Starting Reset", $time);

  drv_init();

  $fdisplay(log, "time=%5d, Reset Completed", $time);

  $fdisplay(log, "time=%5d, Starting Test", $time);
  fork
    drv_request();
    checker();
  join
  $fdisplay(log, "time=%5d, Test Completed", $time);
  $fdisplay(log, "time=%5d, Simulation Completed", $time);
  $fclose(log);
  #200 $finish;
end

scoreboard sb(
.clk (clk),
.D (D),
.enable (enable),
.modo (modo)
);

endmodule

tarea3/clock.v
`timescale 1ns/1ps
module clk (clock);

output clock;
reg clock;

initial begin
clock = 0;
end

always begin
 #5 clock = !clock;
end

endmodule

tarea3/tb_topA.v
`include "clock.v"
`include "contadorA.v"
`include "contadorA_tb.v"

module tb_top;

clk clocks (.clock (clock));

contadorA_tb tb(
.D (D),
.Q (Q),
.enable (enable),
.modo (modo),
.rco (rco),
.clk (clock)
);

count dut (
.D (D),
.Q (Q),
.enable (enable),
.modo (modo),
.rco (rco),
.clk (clock)
);

endmodule

tarea3/output/gtkwave/contadorA_verif.vcd
$date
	Sat May 16 10:55:29 2020
$end
$version
	Icarus Verilog
$end
$timescale
	1ps
$end
$scope module tb_top $end
$var wire 1 ! rco $end
$var wire 2 " modo [1:0] $end
$var wire 1 # enable $end
$var wire 1 $ clock $end
$var wire 4 % Q [3:0] $end
$var wire 4 & D [3:0] $end
$scope module clocks $end
$var reg 1 $ clock $end
$upscope $end
$scope module dut $end
$var wire 1 ' _012_ $end
$var wire 1 ( _014_ $end
$var wire 1 ) _018_ $end
$var wire 1 * _019_ $end
$var wire 1 + _020_ $end
$var wire 1 , _021_ $end
$var wire 1 - _022_ $end
$var wire 1 . _023_ $end
$var wire 1 / _024_ $end
$var wire 1 0 _025_ $end
$var wire 1 1 _026_ $end
$var wire 1 2 _027_ $end
$var wire 1 3 _028_ $end
$var wire 1 4 _029_ $end
$var wire 1 5 _031_ $end
$var wire 1 6 _033_ $end
$var wire 1 7 _034_ $end
$var wire 1 8 _035_ $end
$var wire 1 9 _042_ $end
$var wire 1 : _045_ $end
$var wire 1 ; _046_ $end
$var wire 1 < _047_ $end
$var wire 1 $ clk $end
$var wire 2 = modo [1:0] $end
$var wire 1 # enable $end
$var wire 32 > _044_ [31:0] $end
$var wire 32 ? _043_ [31:0] $end
$var wire 32 @ _041_ [31:0] $end
$var wire 32 A _040_ [31:0] $end
$var wire 32 B _039_ [31:0] $end
$var wire 4 C _038_ [3:0] $end
$var wire 4 D _037_ [3:0] $end
$var wire 16 E _036_ [15:0] $end
$var wire 1 F _032_ $end
$var wire 4 G _030_ [3:0] $end
$var wire 2 H _017_ [1:0] $end
$var wire 4 I _016_ [3:0] $end
$var wire 4 J _015_ [3:0] $end
$var wire 2 K _013_ [1:0] $end
$var wire 2 L _011_ [1:0] $end
$var wire 2 M _010_ [1:0] $end
$var wire 2 N _009_ [1:0] $end
$var wire 2 O _008_ [1:0] $end
$var wire 2 P _007_ [1:0] $end
$var wire 2 Q _006_ [1:0] $end
$var wire 2 R _005_ [1:0] $end
$var wire 2 S _004_ [1:0] $end
$var wire 2 T _003_ [1:0] $end
$var wire 32 U _002_ [31:0] $end
$var wire 1 V _001_ $end
$var wire 4 W _000_ [3:0] $end
$var wire 4 X D [3:0] $end
$var reg 4 Y Q [3:0] $end
$var reg 1 ! rco $end
$upscope $end
$scope module tb $end
$var wire 4 Z Q [3:0] $end
$var wire 1 $ clk $end
$var wire 1 ! rco $end
$var reg 4 [ D [3:0] $end
$var reg 1 # enable $end
$var reg 2 \ modo [1:0] $end
$var integer 32 ] log [31:0] $end
$scope module sb $end
$var wire 4 ^ D [3:0] $end
$var wire 1 $ clk $end
$var wire 1 # enable $end
$var wire 2 _ modo [1:0] $end
$var reg 4 ` sb_Q [3:0] $end
$var reg 1 a sb_rco $end
$upscope $end
$scope task checker $end
$upscope $end
$scope task drv_init $end
$upscope $end
$scope task drv_request $end
$upscope $end
$upscope $end
$upscope $end
$enddefinitions $end
#0
$dumpvars
xa
bx `
bx _
bx ^
b10 ]
bx \
bx [
bx Z
bx Y
bx X
bx W
xV
bzxxxx U
bx T
bzx S
bx R
bx Q
bx P
bx O
bx N
bx M
bx L
bzx K
bzxz J
bxzz I
bx H
bx G
xF
bx E
bx D
bx C
bzxxxz B
bzxxzz A
bzxxz @
bzxxz ?
bzxzz >
bx =
x<
x;
x:
x9
x8
x7
x6
x5
x4
x3
x2
x1
x0
x/
x.
x-
x,
x+
x*
x)
x(
x'
bx &
bx %
0$
x#
bx "
x!
$end
#5000
1$
#10000
b1111 W
1V
1#
b1111 C
b1111 D
1F
19
15
b1 Q
b1 L
b1 M
b1 O
b1 N
0,
b1 P
b1 G
b1111 E
08
07
06
b0 H
1'
1.
1-
b11 "
b11 =
b11 \
b11 _
b1111 &
b1111 X
b1111 [
b1111 ^
0$
#15000
1/
04
03
0+
02
01
00
1)
0;
bz111z B
0:
1*
1(
bz11zz A
0<
b0 R
bz1zz >
b0zz I
b11 T
bz11z ?
bz0z J
bz1 S
bz1 K
bz11z @
bz0000 U
1!
b1111 %
b1111 Y
b1111 Z
0a
b1111 `
1$
#20000
b0 W
b0 C
b0 D
b0 L
b10 Q
b0 M
b0 O
b0 N
1,
b1000 G
b10 P
b0 E
18
07
06
b11 H
0'
1.
1-
b0 "
b0 =
b0 \
b0 _
0$
#25000
0V
0F
05
b1 W
b0 Q
b1 C
b0 G
b1 D
0/
b10 L
b0 O
14
13
1+
b0 N
01
10
02
1*
0(
1)
b11 R
b1000000000000 E
bz1 S
bz111z B
bz0 K
bz1z J
bz00z ?
bz0zz >
bz00z @
b1 T
b11zz I
bz0001 U
b0 %
b0 Y
b0 Z
1a
b0 `
1$
#30000
0$
#35000
b10 W
b10 C
b10 D
14
12
13
b0 L
0)
b10 M
00
1;
1(
b0 T
b10000000000000 E
bz11z ?
bz1 K
1:
bz000z B
bz0010 U
0!
b1 %
b1 Y
b1 Z
b1 `
0a
1$
#40000
b0 &
b0 X
b0 [
b0 ^
0$
#45000
b11 W
b11 C
b11 D
11
b10 L
03
0*
02
b11000000000000 E
1)
bz0 S
0:
bz0011 U
bz000z B
b1 T
bz0z J
b10 %
b10 Y
b10 Z
b10 `
1$
#50000
0$
#55000
b100 W
b100 C
b10 O
b100 D
04
b0 L
b0 M
01
bz1zz >
1*
bz00zz A
1<
b10 R
b100000000000000 E
bz1 S
bz01z @
bz001z B
bz0100 U
b11 %
b11 Y
b11 Z
b11 `
1$
#60000
0$
#65000
b101 W
b101 C
b0 N
b101 D
b10 L
b10 O
b11 R
0<
0;
b101000000000000 E
bz1 S
bz001z B
bz0 K
bz10z ?
bz1z J
b11 T
bz00z @
b10zz I
bz0101 U
b100 %
b100 Y
b100 Z
b100 `
1$
#70000
0$
#75000
b110 W
b110 C
b110 D
b0 L
b10 M
b10 T
b110000000000000 E
bz11z ?
bz1 K
1:
bz010z B
bz0110 U
b101 %
b101 Y
b101 Z
b101 `
1$
#80000
0$
#85000
b111 W
b111 C
b111 D
b10 L
b111000000000000 E
bz0 S
0:
bz0111 U
bz010z B
b11 T
bz0z J
b110 %
b110 Y
b110 Z
b110 `
1$
#90000
0$
#95000
b1000 W
b10 N
b1000 C
b0 O
b1000 D
b0 L
b0 M
bz01zz A
b10 R
b1000000000000000 E
bz1 S
bz11z @
bz011z B
bz1000 U
b111 %
b111 Y
b111 Z
b111 `
1$
#100000
0$
#105000
b1001 W
b1001 C
b1001 D
b10 L
b0 O
b10 N
b11 R
b1001000000000000 E
bz1 S
bz011z B
b11 T
bz0 K
bz1z J
bz00z ?
bz0zz >
bz00z @
b1zz I
bz1001 U
b1000 %
b1000 Y
b1000 Z
b1000 `
1$
#110000
0$
#115000
b1010 W
b1010 C
b1010 D
b0 L
b10 M
1;
b10 T
b1010000000000000 E
bz11z ?
bz1 K
1:
bz100z B
bz1010 U
b1001 %
b1001 Y
b1001 Z
b1001 `
1$
#120000
0$
#125000
b1011 W
b1011 C
b1011 D
b10 L
b1011000000000000 E
bz0 S
0:
bz1011 U
bz100z B
b11 T
bz0z J
b1010 %
b1010 Y
b1010 Z
b1010 `
1$
#130000
0$
#135000
b1100 W
b1100 C
b10 O
b1100 D
b0 L
b0 M
bz1zz >
bz10zz A
1<
b10 R
b1100000000000000 E
bz1 S
bz01z @
bz101z B
bz1100 U
b1011 %
b1011 Y
b1011 Z
b1011 `
1$
#140000
0$
#145000
b1101 W
b1101 C
b10 N
b1101 D
b10 L
b10 O
0<
0;
b1 R
b1101000000000000 E
bz1 S
bz101z B
b11 T
bz0 K
bz10z ?
bz1z J
bz00z @
b0zz I
bz1101 U
b1100 %
b1100 Y
b1100 Z
b1100 `
1$
#150000
0$
#155000
b1110 W
b1110 C
b1110 D
b0 L
b10 M
b10 T
b1110000000000000 E
bz11z ?
bz1 K
1:
bz110z B
bz1110 U
b1101 %
b1101 Y
b1101 Z
b1101 `
1$
#160000
0$
#165000
b1111 W
b1111 C
b1111 D
b10 L
b1111000000000000 E
bz0 S
0:
bz1111 U
bz110z B
b11 T
bz0z J
b1110 %
b1110 Y
b1110 Z
b1110 `
1$
#170000
0$
#175000
1V
1F
15
b0 W
b0 N
b10 Q
b0 C
b0 O
b1000 G
b0 D
1/
b0 L
0+
b0 M
bz11zz A
b0 R
b0 E
bz1 S
bz11z @
bz111z B
bz0000 U
b1111 %
b1111 Y
b1111 Z
b1111 `
1$
#180000
0$
#185000
0V
0F
05
b1 W
b0 Q
b1 C
b0 G
b1 D
0/
b10 L
b0 O
14
13
1+
b0 N
01
10
02
1*
0(
1)
b11 R
b1000000000000 E
bz1 S
bz111z B
bz0 K
bz1z J
bz00z ?
bz0zz >
bz00z @
b1 T
b11zz I
bz0001 U
b0 %
b0 Y
b0 Z
1!
1a
b0 `
1$
#190000
0$
#195000
b10 W
b10 C
b10 D
14
12
13
b0 L
0)
b10 M
00
1;
1(
b0 T
b10000000000000 E
bz11z ?
bz1 K
1:
bz000z B
bz0010 U
0!
b1 %
b1 Y
b1 Z
b1 `
0a
1$
#200000
b0 W
b0 D
b0 C
b0 M
19
17
0.
b0 E
b10 P
08
b10 H
1'
b1 "
b1 =
b1 \
b1 _
0$
#205000
1V
b10 N
b1111 W
1F
15
b1111 C
b10 O
b10 Q
b1111 D
02
b100 G
b10 L
1)
b10 M
10
0;
0(
b1 T
b111100000000 E
bz00z ?
bz0 K
0:
bz111z B
bz0001 U
b0 %
b0 Y
b0 Z
b0 `
1$
#210000
0$
#215000
0V
b1110 W
0F
05
b1110 C
b0 Q
b1110 D
04
1/
03
b0 G
b0 L
0+
b10 M
00
1(
b0 R
b111000000000 E
b11 T
bz1zz >
b0zz I
bz11z ?
bz0z J
bz1 K
0:
bz11z @
bz0000 U
bz111z B
1!
b1111 %
b1111 Y
b1111 Z
1a
b1111 `
1$
#220000
0$
#225000
b1101 W
b1101 C
b1101 D
0/
b10 L
1+
b0 M
bz10zz A
b1 R
b110100000000 E
bz0 S
bz00z @
bz110z B
bz1111 U
b1110 %
b1110 Y
b1110 Z
0!
b1110 `
0a
1$
#230000
0$
#235000
b1100 W
b1100 C
b10 O
b1100 D
b0 L
b0 M
1:
b10 T
b110000000000 E
bz11z ?
bz1z J
bz1 S
bz1110 U
bz110z B
b1101 %
b1101 Y
b1101 Z
b1101 `
1$
#240000
0$
#245000
b1011 W
b1011 C
b0 O
b1011 D
b10 L
b10 M
b11 T
b101100000000 E
bz10z ?
bz0 K
0:
bz101z B
bz1101 U
b1100 %
b1100 Y
b1100 Z
b1100 `
1$
#250000
0$
#255000
b1010 W
b1010 C
b10 N
b1010 D
b0 L
b10 M
bz10zz A
1;
1<
b10 R
b101000000000 E
bz1zz >
b1zz I
bz11z ?
bz0z J
bz1 K
0:
bz01z @
bz1100 U
bz101z B
b1011 %
b1011 Y
b1011 Z
b1011 `
1$
#260000
0$
#265000
b1001 W
b1001 C
b1001 D
b10 L
b0 M
bz0zz >
bz01zz A
0<
b11 R
b100100000000 E
bz0 S
bz00z @
bz100z B
bz1011 U
b1010 %
b1010 Y
b1010 Z
b1010 `
1$
#270000
0$
#275000
b1000 W
b10 N
b1000 C
b0 O
b1000 D
b0 L
b0 M
1;
1:
b10 T
b100000000000 E
bz11z ?
bz1z J
bz1 S
bz1010 U
bz100z B
b1001 %
b1001 Y
b1001 Z
b1001 `
1$
#280000
0$
#285000
b0 N
b111 W
b111 C
b10 O
b111 D
b10 L
b10 M
0;
b11 T
b11100000000 E
bz00z ?
bz0 K
0:
bz011z B
bz1001 U
b1000 %
b1000 Y
b1000 Z
b1000 `
1$
#290000
0$
#295000
b110 W
b110 C
b110 D
b0 L
b10 M
b10 R
b11000000000 E
bz1zz >
b10zz I
bz11z ?
bz0z J
bz1 K
0:
bz11z @
bz1000 U
bz011z B
b111 %
b111 Y
b111 Z
b111 `
1$
#300000
0$
#305000
b101 W
b101 C
b101 D
b10 L
b0 M
bz00zz A
b11 R
b10100000000 E
bz0 S
bz00z @
bz010z B
bz0111 U
b110 %
b110 Y
b110 Z
b110 `
1$
#310000
0$
#315000
b100 W
b100 C
b10 O
b100 D
b0 L
b0 M
1:
b10 T
b10000000000 E
bz11z ?
bz1z J
bz1 S
bz0110 U
bz010z B
b101 %
b101 Y
b101 Z
b101 `
1$
#320000
0$
#325000
b11 W
b11 C
b0 O
b11 D
b10 L
b10 M
b11 T
b1100000000 E
bz10z ?
bz0 K
0:
bz001z B
bz0101 U
b100 %
b100 Y
b100 Z
b100 `
1$
#330000
0$
#335000
b10 W
b10 C
b0 N
b10 D
b0 L
b10 M
bz00zz A
1;
1<
b10 R
b1000000000 E
b1 T
bz1zz >
b11zz I
bz11z ?
bz0z J
bz1 K
0:
bz01z @
bz0100 U
bz001z B
b11 %
b11 Y
b11 Z
b11 `
1$
#340000
0$
#345000
b1 W
b1 C
b1 D
14
b10 L
b0 M
11
bz0zz >
0*
bz11zz A
0<
b11 R
b100000000 E
bz0 S
bz00z @
bz000z B
bz0011 U
b10 %
b10 Y
b10 Z
b10 `
1$
#350000
0$
#355000
b0 W
b0 N
b0 C
b0 O
13
b0 D
12
14
b0 L
0)
b0 M
01
1;
1:
1*
b0 T
b0 E
bz11z ?
bz1z J
bz1 S
bz0010 U
bz000z B
b1 %
b1 Y
b1 Z
b1 `
1$
#360000
1V
1F
15
b1110 D
b1110 W
b1 Q
b1 M
b1 O
b1 N
b1110 C
b10 G
b11100000 E
19
16
0-
b1 P
07
b1 H
1.
b10 "
b10 =
b10 \
b10 _
0$
#365000
0V
0F
b1011 W
05
b1011 C
b0 Q
b1011 D
b0 O
b0 G
04
b1 L
03
02
b10110000 E
bz0 S
bz10zz A
0;
1)
b1 R
0:
bz110z B
bz0z J
bz1zz >
b11 T
b0zz I
bz1111 U
b1110 %
b1110 Y
b1110 Z
1!
1a
b1110 `
1$
#370000
0$
#375000
b1000 W
b1000 C
b1 N
b1000 D
b0 L
b0 M
bz10zz A
1;
1<
b10 R
b10000000 E
bz11z ?
bz1zz >
b1zz I
bz1 S
bz01z @
bz101z B
bz1100 U
0!
b1011 %
b1011 Y
b1011 Z
b1011 `
0a
1$
#380000
0$
#385000
b101 W
b0 N
b101 C
b101 D
b1 O
b1 L
bz0zz >
b1010000 E
0;
bz01zz A
0<
b11 R
bz1 S
bz1001 U
bz011z B
b11 T
bz0 K
bz00z ?
bz00z @
bz1z J
b1000 %
b1000 Y
b1000 Z
b1000 `
1$
#390000
0$
#395000
b10 W
b10 C
b0 O
b10 D
b0 L
b1 M
bz00zz A
b10 T
b100000 E
bz11z ?
bz1zz >
b10zz I
bz1 K
1:
bz010z B
bz0110 U
b101 %
b101 Y
b101 Z
b101 `
1$
#400000
0$
#405000
1V
1F
15
b1111 W
b1 Q
b1111 C
b10 G
b1111 D
14
b1 N
b1 O
11
b1 L
0*
b11110000 E
bz0 S
bz11zz A
1;
0:
bz000z B
bz0z J
b1 T
bz11z ?
bz0zz >
b11zz I
bz0011 U
b10 %
b10 Y
b10 Z
b10 `
1$
#410000
0$
#415000
0V
0F
b1100 W
05
b1100 C
b0 Q
b1100 D
b0 G
1/
04
b0 L
0+
b0 M
01
0;
1*
b0 R
b11000000 E
b11 T
bz1zz >
b0zz I
bz1 S
bz11z @
bz111z B
bz0000 U
1!
b1111 %
b1111 Y
b1111 Z
1a
b1111 `
1$
#420000
0$
#425000
b1001 W
b1001 C
b1001 D
b0 O
0/
b1 L
1+
b10010000 E
bz10zz A
b1 R
bz1 S
bz1101 U
bz101z B
b11 T
bz0 K
bz10z ?
bz00z @
bz1z J
b1100 %
b1100 Y
b1100 Z
0!
b1100 `
0a
1$
#430000
0$
#435000
b110 W
b110 C
b0 N
b1 O
b110 D
b0 L
b1 M
bz01zz A
1;
b11 R
b10 T
b1100000 E
bz11z ?
bz0zz >
b1zz I
bz1 K
1:
bz100z B
bz1010 U
b1001 %
b1001 Y
b1001 Z
b1001 `
1$
#440000
0$
#445000
b11 W
b11 C
b11 D
b0 O
b1 L
b110000 E
bz0 S
bz00zz A
0;
0:
bz010z B
b11 T
bz0z J
bz1zz >
b10zz I
bz0111 U
b110 %
b110 Y
b110 Z
b110 `
1$
#450000
0$
#455000
b0 W
b0 C
b0 N
b0 D
b0 L
b0 M
bz00zz A
1;
1<
b10 R
b0 E
b1 T
bz11z ?
bz1zz >
b11zz I
bz1 S
bz01z @
bz001z B
bz0100 U
b11 %
b11 Y
b11 Z
b11 `
1$
#460000
0$
#465000
1V
1F
b1101 W
15
b1 N
b1101 C
b1 Q
b1101 D
b1 O
b10 G
14
b1 L
13
01
02
10
bz0zz >
1*
b11010000 E
1)
0(
0;
bz11zz A
0<
b11 R
bz1 S
bz0001 U
bz111z B
b1 T
bz0 K
bz00z ?
bz00z @
bz1z J
b0 %
b0 Y
b0 Z
b0 `
1$
#470000
0$
#475000
0V
0F
05
b1010 W
b0 Q
b1010 C
b0 O
b0 G
b1010 D
04
03
b0 L
b1 M
00
bz10zz A
b1 R
1(
b10100000 E
b10 T
bz11z ?
bz1zz >
b0zz I
bz1 K
1:
bz110z B
bz1110 U
1!
b1101 %
b1101 Y
b1101 Z
1a
b1101 `
1$
#480000
0$
#485000
b111 W
b111 C
b111 D
b0 N
b1 O
b1 L
b1110000 E
bz0 S
bz01zz A
1;
b11 R
0:
bz100z B
b11 T
bz0z J
bz11z ?
bz0zz >
b1zz I
bz1011 U
b1010 %
b1010 Y
b1010 Z
0!
b1010 `
0a
1$
#490000
0$
#495000
b100 W
b100 C
b100 D
b0 L
b0 M
0;
b10 R
b1000000 E
bz1zz >
b10zz I
bz1 S
bz11z @
bz011z B
bz1000 U
b111 %
b111 Y
b111 Z
b111 `
1$
#500000
0$
#505000
b1 W
b1 C
b1 D
b0 O
b1 L
b10000 E
bz00zz A
b11 R
bz1 S
bz0101 U
bz001z B
b11 T
bz0 K
bz10z ?
bz00z @
bz1z J
b100 %
b100 Y
b100 Z
b100 `
1$
#510000
0$
#515000
1V
1F
15
b1 Q
b1110 W
b10 G
b1110 C
14
b1 N
b1 O
13
b1110 D
12
b0 L
0)
b1 M
bz11zz A
1;
b11100000 E
b0 T
bz11z ?
bz0zz >
b11zz I
bz1 K
1:
bz000z B
bz0010 U
b1 %
b1 Y
b1 Z
b1 `
1$
#520000
0$
#525000
0V
0F
b1011 W
05
b1011 C
b0 Q
b1011 D
b0 O
b0 G
04
b1 L
03
02
b10110000 E
bz0 S
bz10zz A
0;
1)
b1 R
0:
bz110z B
bz0z J
bz1zz >
b11 T
b0zz I
bz1111 U
b1110 %
b1110 Y
b1110 Z
1!
1a
b1110 `
1$
#530000
0$
#535000
b1000 W
b1000 C
b1 N
b1000 D
b0 L
b0 M
bz10zz A
1;
1<
b10 R
b10000000 E
bz11z ?
bz1zz >
b1zz I
bz1 S
bz01z @
bz101z B
bz1100 U
0!
b1011 %
b1011 Y
b1011 Z
b1011 `
0a
1$
#540000
0$
