ejemplo/Tarea2/Reg32/RegDesp.v
module RegDesp(clk, enb, dir, sIn, modo, D, Q, sOut) ;

  input clk, //clock
        enb, //enabler
        dir, //dir
        sIn; //entrada de dato
  input [1:0] modo; //modo
  input [3:0] D; //entrada de datos

  output reg [3:0] Q;//salida de estado
  output reg sOut; //salida de dato


	always @ (posedge clk) begin
    if(enb) begin//de esta forma solo se ejecutara cuando el enabler este en 1
    //luego se chequea si se quiere a la derecha (dir=1) o a la Izquierda (dir=0)
      if (dir) begin //Rotar Derecha: dir=1
        if (modo==2'b00)begin//se chequea si se quiere una rotacion a la derecha: modo=00
          Q <= {sIn, Q[3:1]};
          sOut <= Q[0];
        end //end modo=00

        else if (modo==2'b01) begin //Rotar Derecha Circular: modo=01
          Q <= {Q[0],Q[3:1]};
          sOut <= 0;//ya que es circular, no hay dato que salga... por ende se saca un 0 por especificacion
        end //modo=01
      end//end dir=1
      else begin //Rotar Izquierda dir=0
        if (modo==2'b00)begin//se chequea si se quiere una rotacion a la izquierda: modo=00
          Q <= {Q[2:0], sIn};
          sOut <= Q[3];
        end //modo=00
        else if (modo==2'b01) begin //Rotar Izquierda Circular: modo=01
          Q <= {Q[2:0],Q[3]};
          sOut <= 0;
        end //modo 01
      end//end dir=0

      if(modo==2'b10) begin//carga Paralelo: Modo=10 & dir=x; esto porque se ignora la direccion
        Q <= D[3:0];
        sOut <= 0;
      end// end carga Paralela

    end//end enb
  end//end always
endmodule

ejemplo/Tarea2/Reg4/tester.v
module tester(clk,enb,dir,sIn,modo,D);
  output reg clk,enb,dir,sIn;
  output reg [1:0] modo;
  output reg [3:0] D;

  always #2 clk = !clk;

  initial begin

    clk <=0;
    enb <= 1;
    dir <= 0;
    sIn <= 1;
    modo <= 2'b00;

    $display("Prueba 1; Rotacion a la Izquierda");
      modo <= 2'b00;
      dir <= 1'b0;
      D <= 4'b0001;
      #16;

    $display("Prueba 5; Carga en Paralelo");
      D <= 4'b0101;
      modo <= 2'b10;
      enb <= 1'b1;
      #4;

    $display("Prueba 2; Rotacion a la Derecha");
      modo <= 2'b00;
    	dir <= 1'b1;
      #16;

    $display("Prueba 5; Carga en Paralelo");
      D <= 4'b0110;
      modo <= 2'b10;
      enb <= 1'b1;
      #4;

    $display("Prueba 3; Rotacion Circular a la Izquierda");
      modo <= 2'b01;
      dir <= 1'b0;
      #16;

    $display("Prueba 5; Carga en Paralelo");
      D <= 4'b1001;
      modo <= 2'b10;
      enb <= 1'b1;
      #4;


    $display("Prueba 4; Rotacion Circular a la Derecha");
      modo <= 2'b01;
    	dir <= 1'b1;
    	#16;


    $finish;
      end
endmodule

ejemplo/Tarea2/Reg4/testbench.v
module testbench();
  wire [3:0] D;
  output wire [3:0] Q;
  wire [1:0] modo;
  tester prueba(clk,enb,dir,sIn,modo,D);
  RegDesp registro(clk,enb,dir,sIn,modo,D,Q,sOut);
  initial begin
    $dumpfile("resultado.vcd");
    $dumpvars;
    $display ("time\t clk  enb  dir  sIn  modo    D       Q    sOut");
    $monitor ("%g\t    %b  %b    %b    %b    %b    %b    %b   %b",
    $time, clk, enb, dir, sIn, modo, D, Q, sOut);
  end
endmodule

ejemplo/Tarea2/Reg4/resultado.vcd
$date
	Tue Apr  3 22:50:39 2018
$end
$version
	Icarus Verilog
$end
$timescale
	1s
$end
$scope module testbench $end
$var wire 4 ! D [3:0] $end
$var wire 4 " Q [3:0] $end
$var wire 1 # clk $end
$var wire 1 $ dir $end
$var wire 1 % enb $end
$var wire 2 & modo [1:0] $end
$var wire 1 ' sIn $end
$var wire 1 ( sOut $end
$scope module prueba $end
$var reg 4 ) D [3:0] $end
$var reg 1 * clk $end
$var reg 1 + dir $end
$var reg 1 , enb $end
$var reg 2 - modo [1:0] $end
$var reg 1 . sIn $end
$upscope $end
$scope module registro $end
$var wire 4 / D [3:0] $end
$var wire 1 # clk $end
$var wire 1 $ dir $end
$var wire 1 % enb $end
$var wire 2 0 modo [1:0] $end
$var wire 1 ' sIn $end
$var reg 4 1 Q [3:0] $end
$var reg 1 2 sOut $end
$upscope $end
$upscope $end
$enddefinitions $end
#0
$dumpvars
x2
bx 1
b0 0
b1 /
1.
b0 -
1,
0+
0*
b1 )
x(
1'
b0 &
1%
0$
0#
bx "
b1 !
$end
#2
bx1 1
bx1 "
1*
1#
#4
0*
0#
#6
bx11 1
bx11 "
1*
1#
#8
0*
0#
#10
bx111 1
bx111 "
1*
1#
#12
0*
0#
#14
b1111 1
b1111 "
1*
1#
#16
b10 -
b10 &
b10 0
b101 )
b101 !
b101 /
0*
0#
#18
02
0(
b101 1
b101 "
1*
1#
#20
1+
1$
b0 -
b0 &
b0 0
0*
0#
#22
12
1(
b1010 1
b1010 "
1*
1#
#24
0*
0#
#26
02
0(
b1101 1
b1101 "
1*
1#
#28
0*
0#
#30
12
1(
b1110 1
b1110 "
1*
1#
#32
0*
0#
#34
02
0(
b1111 1
b1111 "
1*
1#
#36
b10 -
b10 &
b10 0
b110 )
b110 !
b110 /
0*
0#
#38
b110 1
b110 "
1*
1#
#40
0+
0$
b1 -
b1 &
b1 0
0*
0#
#42
b1100 1
b1100 "
1*
1#
#44
0*
0#
#46
b1001 1
b1001 "
1*
1#
#48
0*
0#
#50
b11 1
b11 "
1*
1#
#52
0*
0#
#54
b110 1
b110 "
1*
1#
#56
b10 -
b10 &
b10 0
b1001 )
b1001 !
b1001 /
0*
0#
#58
b1001 1
b1001 "
1*
1#
#60
1+
1$
b1 -
b1 &
b1 0
0*
0#
#62
b1100 1
b1100 "
1*
1#
#64
0*
0#
#66
b110 1
b110 "
1*
1#
#68
0*
0#
#70
b11 1
b11 "
1*
1#
#72
0*
0#
#74
b1001 1
b1001 "
1*
1#
