Proyecto/definitions.v
wire [1:0] modo;
wire [3:0] D;
wire [3:0] Q;

Proyecto/counter.v
module count (enable, clk, modo, D, rco, Q, reset);

//Define output ports
output [3:0] Q;
output rco;
reg [3:0] Q;
reg rco;

//define input ports
input  [3:0] D;
input  [1:0] modo;
input enable;
input clk;
input reset;
wire [3:0] D;
wire [1:0] modo;
wire clock,enable, reset;

reg[3:0]  Qstatus;
reg RCOstatus;

//-------------Internal Constants--------------------------
parameter SIZE = 3           ;
parameter PLUSONE  = 2'b00,MINUSONE  = 2'b01,MINUSTHREE  = 2'b10, LOAD  = 2'b11 ;

//-------------Internal Variables---------------------------



//----------Code starts here------------------------
always @ (posedge clk) begin

  if(enable) begin//de esta forma solo se ejecutara cuando el enabler este en 1
    if (reset == 0) begin
    if (rco == 1) begin
      rco = 1'b0;
    end
    case(modo)
      PLUSONE : if (Q==4'b1111) begin
        Q[3:0] = 4'b0000;
        rco = 1'b1;
      end else begin
        Q[3:0] = Q + 4'b0001;
      end

      MINUSONE : if (Q==4'b0000) begin
        Q[3:0] = 4'b1111;
        rco = 1'b1;
      end else begin
        Q[3:0] = Q - 4'b0001;
      end

      MINUSTHREE : if (Q==4'b0000) begin
        Q[3:0] = 4'b1101;
        rco = 1'b1;
      end else if (Q==4'b0001) begin
        Q[3:0] = 4'b1110;
        rco = 1'b1;
      end else if (Q==4'b0010) begin
        Q[3:0] = 4'b1111;
        rco = 1'b1;
      end else begin
        Q[3:0] = Q - 4'b0011;
      end

      LOAD: begin
        Q[3:0] = D;
        rco = 1'b1;
        end

     endcase
     RCOstatus = rco;
     Qstatus = Q;
    end else begin
      Q[3:0] = 4'b0000;
      rco = 1'b0;
      RCOstatus = rco;
      Qstatus = Q;
    end
  end//end enb
  else begin
  Q[3:0] = Qstatus;
  rco = RCOstatus;
  end

end//end always
endmodule // End of Module counter

Proyecto/checker.v

task checker;

repeat (83) @(negedge clk) begin
	if ({sb.sb_Q,sb.sb_rco} == {Q, rco}) begin
          $fdisplay(log, "PASS");
        end
        else begin
          $fdisplay(log, "Time=%.0f Error dut: Q=%b, rco=%b, scoreboard: Q=%b, rco=%b", $time, Q, rco, sb.sb_Q,sb.sb_rco);
        end
end
endtask

task random_checker;
repeat (10) @(negedge clk) begin
	if ({sb.sb_Q,sb.sb_rco} == {Q, rco}) begin
          $fdisplay(log, "PASS");
        end
        else begin
          $fdisplay(log, "Time=%.0f Error dut: Q=%b, rco=%b, scoreboard: Q=%b, rco=%b", $time, Q, rco, sb.sb_Q,sb.sb_rco);
        end
end
endtask

task completely_random_checker;
repeat (54) @(negedge clk) begin
	if ({sb.sb_Q,sb.sb_rco} == {Q, rco}) begin
          $fdisplay(log, "PASS");
        end
        else begin
          $fdisplay(log, "Time=%.0f Error dut: Q=%b, rco=%b, scoreboard: Q=%b, rco=%b", $time, Q, rco, sb.sb_Q,sb.sb_rco);
        end
end
endtask

Proyecto/driver.v
//Init task for clean output signals
task drv_init;
  begin
    @(negedge clk) begin
      enable <= 1'b0;
      D = 4'b1111;
      modo = 2'b11;
      reset = 1'b1;
    end
    @(negedge clk) begin
      enable = 1;
      modo = 2'b11;
      reset = 1'b1;
    end
    #40@(negedge clk);
    @(negedge clk) begin
      enable = 1;
      modo = 2'b00;
      reset = 1'b0;
    end
  end
endtask

//Drive request to the arbiter
task drv_request;
begin
@(negedge clk);
enable <= 1'b1;
D = 4'b0000;
modo = 2'b00;
#160 @(negedge clk);
modo = 2'b01;
#80 @(negedge clk);
modo = 2'b10;
#80 @(negedge clk);
D = 4'b1111;
#160 @(negedge clk);
modo = 2'b11;
#10 @(negedge clk);
modo =2'b00;
reset = 1;
#10 @(negedge clk);
modo =2'b00;
reset = 0;
#50@(negedge clk);
enable = 0;
#50@(negedge clk);
enable = 0;
#30@(negedge clk);
enable = 1;
#30@(negedge clk);
D = 4'b1111;
#10 @(negedge clk);
modo = 2'b01;
#160 @(negedge clk);

end
endtask

task drv_random_request;
  begin
    repeat (20) begin
      @(negedge clk) begin
        enable = $random;
        D = $random;
      end
    end
  end
endtask

task drv_completely_random_request;
  begin
    repeat (6) begin
    @(negedge clk)
    modo  = $random;
      repeat (10) begin
        @(negedge clk) begin
          enable = $random;
          D = $random;
        end
      end
    end
  end
endtask

Proyecto/scoreboard.v
`timescale 1ns/1ps
//Scoreboard
module scoreboard (D, modo, enable, clk, reset) ;

input [3:0] D;
input clk;
input enable;
input [1:0] modo;
input reset;



//wire  sb_rco;
reg sb_rco;
reg [3:0] sb_Q;

//UPDATE THIS SECTION
always @(posedge clk)
begin



  if (enable == 1'b1) begin

  if (reset == 0) begin
    if (modo == 2'b00) begin//Check add 1

      if (sb_rco == 1'b1) begin //Check carry out
        sb_rco = 1'b0;
      end

      if (sb_Q < 4'b1111) begin //Check if add
        sb_Q[3:0] = sb_Q + 4'b0001;
      end
      else begin //Rebase
        sb_Q = 4'b0000;
        sb_rco = 1'b1;
      end
    end

    if (modo == 2'b01) begin //Check substract 1

      if (sb_rco == 1'b1) begin //Check carry out
        sb_rco = 1'b0;
      end

      if (sb_Q > 4'b0000) begin //Check if add
        sb_Q[3:0] = sb_Q - 4'b0001;
      end
      else begin //Rebase
        sb_Q = 4'b1111;
        sb_rco = 1'b1;
      end

    end
    if (modo == 2'b10) begin

      if (sb_rco == 1'b1) begin //Check carry out
        sb_rco = 1'b0;
      end

      if (sb_Q > 4'b0010) begin //Check if add
        sb_Q[3:0] = sb_Q - 4'b0011;
      end
      else begin //Rebase
        if (sb_Q == 4'b0010) begin
          sb_Q = 4'b1111;
          sb_rco = 1'b1;
        end
        else if (sb_Q == 4'b0001) begin
          sb_Q = 4'b1110;
          sb_rco = 1'b1;
        end
        else begin
          sb_Q = 4'b1101;
          sb_rco = 1'b1;
        end

      end

    end
    if (modo == 2'b11) begin

      sb_Q[3:0] = D;
      sb_rco = 1'b1;
    end
  end else begin
    sb_Q = 4'b0000;
    sb_rco = 1'b0;
  end


  end//enable
end

endmodule

Proyecto/conductual_tb.v
//`timescale 1ns/1ps
// Testbench Code Goes here
`include "scoreboard.v"

module conductual_tb( enable, modo, D, rco, Q, clk, reset);

input [3:0] Q;
output [3:0] D;
reg [3:0] D;
input clk;
input rco;
output [1:0] modo;
reg [1:0] modo;
output enable;
reg enable;
output reset;
reg reset;

`include "driver.v"
`include "checker.v"


integer log;

initial begin

  $dumpfile("output/gtkwave/conductual_verif.vcd");
  $dumpvars(0);

  log = $fopen("output/logs/conductual.log");
  $fdisplay(log, "time=%5d, Simulation Start", $time);
  $fdisplay(log, "time=%5d, Starting Reset", $time);

  drv_init();

  $fdisplay(log, "time=%5d, Reset Completed", $time);

  $fdisplay(log, "time=%5d, Starting Test", $time);

  $fdisplay(log, "time=%5d, Starting Semi Random Test", $time);
  fork
    drv_random_request();
    random_checker();
  join
  $fdisplay(log, "time=%5d, Starting Completely Random Test", $time);
  fork
    drv_completely_random_request();
    completely_random_checker();
  join
  $fdisplay(log, "time=%5d, Starting Scripted Test", $time);
  fork
    drv_request();
    checker();
  join
  $fdisplay(log, "time=%5d, Test Completed", $time);
  $fdisplay(log, "time=%5d, Simulation Completed", $time);
  $fclose(log);
  #200 $finish;
end

scoreboard sb(
.clk (clk),
.D (D),
.enable (enable),
.modo (modo),
.reset (reset)
);

endmodule

tarea3/clock.v
`timescale 1ns/1ps
module clk (clock);

output clock;
reg clock;

initial begin
clock = 0;
end

always begin
 #5 clock = !clock;
end

endmodule

Proyecto/tb_top_conductual.v
`timescale 1ns/1ps
`include "clock.v"
`include "counter.v"
`include "conductual_tb.v"

module tb_top;
`include "definitions.v"

clk clocks (.clock (clock));

conductual_tb tb(
.D (D),
.Q (Q),
.enable (enable),
.modo (modo),
.rco (rco),
.clk (clock),
.reset (reset)
);

count dut (
.D (D),
.Q (Q),
.enable (enable),
.modo (modo),
.rco (rco),
.clk (clock),
.reset (reset)
);

endmodule

Proyecto/output/gtkwave/conductual_verif.vcd
$date
	Fri Jul 10 00:40:53 2020
$end
$version
	Icarus Verilog
$end
$timescale
	1ps
$end
$scope module tb_top $end
$var wire 1 ! reset $end
$var wire 1 " rco $end
$var wire 2 # modo [1:0] $end
$var wire 1 $ enable $end
$var wire 1 % clock $end
$var wire 4 & Q [3:0] $end
$var wire 4 ' D [3:0] $end
$scope module clocks $end
$var reg 1 % clock $end
$upscope $end
$scope module dut $end
$var wire 1 % clk $end
$var wire 1 ! reset $end
$var wire 2 ( modo [1:0] $end
$var wire 1 $ enable $end
$var wire 4 ) D [3:0] $end
$var reg 4 * Q [3:0] $end
$var reg 4 + Qstatus [3:0] $end
$var reg 1 , RCOstatus $end
$var reg 1 " rco $end
$upscope $end
$scope module tb $end
$var wire 4 - Q [3:0] $end
$var wire 1 % clk $end
$var wire 1 " rco $end
$var reg 4 . D [3:0] $end
$var reg 1 $ enable $end
$var reg 2 / modo [1:0] $end
$var reg 1 ! reset $end
$var integer 32 0 log [31:0] $end
$scope module sb $end
$var wire 4 1 D [3:0] $end
$var wire 1 % clk $end
$var wire 1 $ enable $end
$var wire 2 2 modo [1:0] $end
$var wire 1 ! reset $end
$var reg 4 3 sb_Q [3:0] $end
$var reg 1 4 sb_rco $end
$upscope $end
$scope task checker $end
$upscope $end
$scope task completely_random_checker $end
$upscope $end
$scope task drv_completely_random_request $end
$upscope $end
$scope task drv_init $end
$upscope $end
$scope task drv_random_request $end
$upscope $end
$scope task drv_request $end
$upscope $end
$scope task random_checker $end
$upscope $end
$upscope $end
$upscope $end
$enddefinitions $end
#0
$dumpvars
x4
bx 3
bx 2
bx 1
b10 0
bx /
bx .
bx -
x,
bx +
bx *
bx )
bx (
bx '
bx &
0%
x$
bx #
x"
x!
$end
#2000
1%
#4000
0$
1!
b11 #
b11 (
b11 /
b11 2
b1111 '
b1111 )
b1111 .
b1111 1
0%
#6000
1%
#8000
1$
0%
#10000
04
b0 3
b0 +
0,
0"
b0 &
b0 *
b0 -
1%
#12000
0%
#14000
1%
#16000
0%
#18000
1%
#20000
0%
#22000
1%
#24000
0%
#26000
1%
#28000
0%
#30000
1%
#32000
0%
#34000
1%
#36000
0%
#38000
1%
#40000
0%
#42000
1%
#44000
0%
#46000
1%
#48000
0%
#50000
1%
#52000
0!
b0 #
b0 (
b0 /
b0 2
0%
#54000
b1 +
b1 &
b1 *
b1 -
b1 3
1%
#56000
b1 '
b1 )
b1 .
b1 1
0$
0%
#58000
1%
#60000
b11 '
b11 )
b11 .
b11 1
1$
0%
#62000
b10 +
b10 &
b10 *
b10 -
b10 3
1%
#64000
b1101 '
b1101 )
b1101 .
b1101 1
0%
#66000
b11 3
b11 +
b11 &
b11 *
b11 -
1%
#68000
b10 '
b10 )
b10 .
b10 1
0%
#70000
b100 +
b100 &
b100 *
b100 -
b100 3
1%
#72000
b1101 '
b1101 )
b1101 .
b1101 1
0%
#74000
b101 3
b101 +
b101 &
b101 *
b101 -
1%
#76000
0$
0%
#78000
1%
#80000
b1100 '
b1100 )
b1100 .
b1100 1
1$
0%
#82000
b110 3
b110 +
b110 &
b110 *
b110 -
1%
#84000
b110 '
b110 )
b110 .
b110 1
0%
#86000
b111 +
b111 &
b111 *
b111 -
b111 3
1%
#88000
b1010 '
b1010 )
b1010 .
b1010 1
0%
#90000
b1000 3
b1000 +
b1000 &
b1000 *
b1000 -
1%
#92000
b111 '
b111 )
b111 .
b111 1
0%
#94000
b1001 +
b1001 &
b1001 *
b1001 -
b1001 3
1%
#96000
b1111 '
b1111 )
b1111 .
b1111 1
0$
0%
#98000
1%
#100000
b1110 '
b1110 )
b1110 .
b1110 1
0%
#102000
1%
#104000
b101 '
b101 )
b101 .
b101 1
0%
#106000
1%
#108000
b1101 '
b1101 )
b1101 .
b1101 1
0%
#110000
1%
#112000
b101 '
b101 )
b101 .
b101 1
1$
0%
#114000
b1010 3
b1010 +
b1010 &
b1010 *
b1010 -
1%
#116000
b1010 '
b1010 )
b1010 .
b1010 1
0%
#118000
b1011 +
b1011 &
b1011 *
b1011 -
b1011 3
1%
#120000
b0 '
b0 )
b0 .
b0 1
0$
0%
#122000
1%
#124000
b1101 '
b1101 )
b1101 .
b1101 1
0%
#126000
1%
#128000
b11 '
b11 )
b11 .
b11 1
0%
#130000
1%
#132000
1$
0%
#134000
b1100 +
b1100 &
b1100 *
b1100 -
b1100 3
1%
#136000
b11 #
b11 (
b11 /
b11 2
0%
#138000
14
b11 3
b11 +
1,
1"
b11 &
b11 *
b11 -
1%
#140000
b10 '
b10 )
b10 .
b10 1
0%
#142000
b10 +
b10 &
b10 *
b10 -
1"
b10 3
1%
#144000
b1101 '
b1101 )
b1101 .
b1101 1
0$
0%
#146000
1%
#148000
b11 '
b11 )
b11 .
b11 1
1$
0%
#150000
b11 +
b11 &
b11 *
b11 -
1"
b11 3
1%
#152000
b1010 '
b1010 )
b1010 .
b1010 1
0$
0%
#154000
1%
#156000
b10 '
b10 )
b10 .
b10 1
0%
#158000
1%
#160000
b1 '
b1 )
b1 .
b1 1
0%
#162000
1%
#164000
b1000 '
b1000 )
b1000 .
b1000 1
0%
#166000
1%
#168000
b1011 '
b1011 )
b1011 .
b1011 1
1$
0%
#170000
b1011 3
b1011 +
b1011 &
b1011 *
b1011 -
1"
1%
#172000
b110 '
b110 )
b110 .
b110 1
0$
0%
#174000
1%
#176000
b1100 '
b1100 )
b1100 .
b1100 1
0%
#178000
1%
#180000
b10 #
b10 (
b10 /
b10 2
0%
#182000
1%
#184000
b1 '
b1 )
b1 .
b1 1
1$
0%
#186000
b1000 3
04
b1000 +
0,
b1000 &
b1000 *
b1000 -
0"
1%
#188000
b1111 '
b1111 )
b1111 .
b1111 1
0%
#190000
b101 +
b101 &
b101 *
b101 -
b101 3
1%
#192000
b1010 '
b1010 )
b1010 .
b1010 1
0%
#194000
b10 3
b10 +
b10 &
b10 *
b10 -
1%
#196000
b101 '
b101 )
b101 .
b101 1
0$
0%
#198000
1%
#200000
b1001 '
b1001 )
b1001 .
b1001 1
1$
0%
#202000
14
b1111 3
b1111 +
1,
1"
b1111 &
b1111 *
b1111 -
1%
#204000
b1100 '
b1100 )
b1100 .
b1100 1
0$
0%
#206000
1%
#208000
b1111 '
b1111 )
b1111 .
b1111 1
1$
0%
#210000
b1100 3
04
b1100 +
0,
b1100 &
b1100 *
b1100 -
0"
1%
#212000
b111 '
b111 )
b111 .
b111 1
0$
0%
#214000
1%
#216000
b1100 '
b1100 )
b1100 .
b1100 1
1$
0%
#218000
b1001 3
b1001 +
b1001 &
b1001 *
b1001 -
1%
#220000
b1001 '
b1001 )
b1001 .
b1001 1
0%
#222000
b110 +
b110 &
b110 *
b110 -
b110 3
1%
#224000
b1 #
b1 (
b1 /
b1 2
0%
#226000
b101 3
b101 +
b101 &
b101 *
b101 -
1%
#228000
b111 '
b111 )
b111 .
b111 1
0$
0%
#230000
1%
#232000
b110 '
b110 )
b110 .
b110 1
1$
0%
#234000
b100 3
b100 +
b100 &
b100 *
b100 -
1%
#236000
b10 '
b10 )
b10 .
b10 1
0$
0%
#238000
1%
#240000
b111 '
b111 )
b111 .
b111 1
0%
#242000
1%
#244000
b10 '
b10 )
b10 .
b10 1
1$
0%
#246000
b11 +
b11 &
b11 *
b11 -
b11 3
1%
#248000
b1101 '
b1101 )
b1101 .
b1101 1
0$
0%
#250000
1%
#252000
b1111 '
b1111 )
b1111 .
b1111 1
1$
0%
#254000
b10 +
b10 &
b10 *
b10 -
b10 3
1%
#256000
b101 '
b101 )
b101 .
b101 1
0%
#258000
b1 3
b1 +
b1 &
b1 *
b1 -
1%
#260000
b1011 '
b1011 )
b1011 .
b1011 1
0$
0%
#262000
1%
#264000
b1111 '
b1111 )
b1111 .
b1111 1
1$
0%
#266000
b0 3
b0 +
b0 &
b0 *
b0 -
1%
#268000
b10 #
b10 (
b10 /
b10 2
0%
#270000
b1101 +
1,
1"
b1101 &
b1101 *
b1101 -
14
b1101 3
1%
#272000
b110 '
b110 )
b110 .
b110 1
0$
0%
#274000
1%
#276000
b1100 '
b1100 )
b1100 .
b1100 1
0%
#278000
1%
#280000
b110 '
b110 )
b110 .
b110 1
0%
#282000
1%
#284000
b11 '
b11 )
b11 .
b11 1
1$
0%
#286000
b1010 +
0,
b1010 &
b1010 *
b1010 -
0"
b1010 3
04
1%
#288000
0%
#290000
b111 3
b111 +
b111 &
b111 *
b111 -
1%
#292000
b100 '
b100 )
b100 .
b100 1
0%
#294000
b100 +
b100 &
b100 *
b100 -
b100 3
1%
#296000
b1011 '
b1011 )
b1011 .
b1011 1
0%
#298000
b1 3
b1 +
b1 &
b1 *
b1 -
1%
#300000
b1010 '
b1010 )
b1010 .
b1010 1
0$
0%
#302000
1%
#304000
b1101 '
b1101 )
b1101 .
b1101 1
1$
0%
#306000
14
b1110 3
b1110 +
1,
1"
b1110 &
b1110 *
b1110 -
1%
#308000
b101 '
b101 )
b101 .
b101 1
0$
0%
#310000
1%
#312000
b1 #
b1 (
b1 /
b1 2
0%
#314000
1%
#316000
b1001 '
b1001 )
b1001 .
b1001 1
1$
0%
#318000
b1101 +
0,
b1101 &
b1101 *
b1101 -
0"
b1101 3
04
1%
#320000
b0 '
b0 )
b0 .
b0 1
0$
0%
#322000
1%
#324000
b1011 '
b1011 )
b1011 .
b1011 1
0%
#326000
1%
#328000
b1100 '
b1100 )
b1100 .
b1100 1
0%
#330000
1%
#332000
b1101 '
b1101 )
b1101 .
b1101 1
0%
#334000
1%
#336000
b110 '
b110 )
b110 .
b110 1
1$
0%
#338000
b1100 3
b1100 +
b1100 &
b1100 *
b1100 -
1%
#340000
b111 '
b111 )
b111 .
b111 1
0$
0%
#342000
1%
#344000
b110 '
b110 )
b110 .
b110 1
0%
#346000
1%
#348000
b1001 '
b1001 )
b1001 .
b1001 1
0%
#350000
1%
#352000
b100 '
b100 )
b100 .
b100 1
0%
#354000
1%
#356000
b11 #
b11 (
b11 /
b11 2
0%
#358000
1%
#360000
b1001 '
b1001 )
b1001 .
b1001 1
0%
#362000
1%
#364000
b1101 '
b1101 )
b1101 .
b1101 1
1$
0%
#366000
b1101 +
1,
1"
b1101 &
b1101 *
b1101 -
14
b1101 3
1%
#368000
0%
#370000
1"
1%
#372000
b1010 '
b1010 )
b1010 .
b1010 1
0$
0%
#374000
1%
#376000
b101 '
b101 )
b101 .
b101 1
0%
#378000
1%
#380000
b100 '
b100 )
b100 .
b100 1
0%
#382000
1%
#384000
b1001 '
b1001 )
b1001 .
b1001 1
1$
0%
#386000
b1001 3
b1001 +
b1001 &
b1001 *
b1001 -
1"
1%
#388000
b1000 '
b1000 )
b1000 .
b1000 1
0$
0%
#390000
1%
#392000
b1101 '
b1101 )
b1101 .
b1101 1
0%
#394000
1%
#396000
b1110 '
b1110 )
b1110 .
b1110 1
1$
0%
#398000
b1110 +
b1110 &
b1110 *
b1110 -
1"
b1110 3
1%
#400000
b0 #
b0 (
b0 /
b0 2
b0 '
b0 )
b0 .
b0 1
0%
#402000
b1111 3
04
b1111 +
0,
b1111 &
b1111 *
b1111 -
0"
1%
#404000
0%
#406000
b0 +
1,
1"
b0 &
b0 *
b0 -
14
b0 3
1%
#408000
0%
#410000
b1 3
04
b1 +
0,
b1 &
b1 *
b1 -
0"
1%
#412000
0%
#414000
b10 +
b10 &
b10 *
b10 -
b10 3
1%
#416000
0%
#418000
b11 3
b11 +
b11 &
b11 *
b11 -
1%
#420000
0%
#422000
b100 +
b100 &
b100 *
b100 -
b100 3
1%
#424000
0%
#426000
b101 3
b101 +
b101 &
b101 *
b101 -
1%
#428000
0%
#430000
b110 +
b110 &
b110 *
b110 -
b110 3
1%
#432000
0%
#434000
b111 3
b111 +
b111 &
b111 *
b111 -
1%
#436000
0%
#438000
b1000 +
b1000 &
b1000 *
b1000 -
b1000 3
1%
#440000
0%
#442000
b1001 3
b1001 +
b1001 &
b1001 *
b1001 -
1%
#444000
0%
#446000
b1010 +
b1010 &
b1010 *
b1010 -
b1010 3
1%
#448000
0%
#450000
b1011 3
b1011 +
b1011 &
b1011 *
b1011 -
1%
#452000
0%
#454000
b1100 +
b1100 &
b1100 *
b1100 -
b1100 3
1%
#456000
0%
#458000
b1101 3
b1101 +
b1101 &
b1101 *
b1101 -
1%
#460000
0%
#462000
b1110 +
b1110 &
b1110 *
b1110 -
b1110 3
1%
#464000
0%
#466000
b1111 3
b1111 +
b1111 &
b1111 *
b1111 -
1%
#468000
0%
#470000
b0 +
1,
1"
b0 &
b0 *
b0 -
14
b0 3
1%
#472000
0%
#474000
b1 3
04
b1 +
0,
b1 &
b1 *
b1 -
0"
1%
#476000
0%
#478000
b10 +
b10 &
b10 *
b10 -
b10 3
1%
#480000
0%
#482000
b11 3
b11 +
b11 &
b11 *
b11 -
1%
#484000
0%
#486000
b100 +
b100 &
b100 *
b100 -
b100 3
1%
#488000
0%
#490000
b101 3
b101 +
b101 &
b101 *
b101 -
1%
#492000
0%
#494000
b110 +
b110 &
b110 *
b110 -
b110 3
1%
#496000
0%
#498000
b111 3
b111 +
b111 &
b111 *
b111 -
1%
#500000
0%
#502000
b1000 +
b1000 &
b1000 *
b1000 -
b1000 3
1%
#504000
0%
#506000
b1001 3
b1001 +
b1001 &
b1001 *
b1001 -
1%
#508000
0%
#510000
b1010 +
b1010 &
b1010 *
b1010 -
b1010 3
1%
#512000
0%
#514000
b1011 3
b1011 +
b1011 &
b1011 *
b1011 -
1%
#516000
0%
#518000
b1100 +
b1100 &
b1100 *
b1100 -
b1100 3
1%
#520000
0%
#522000
b1101 3
b1101 +
b1101 &
b1101 *
b1101 -
1%
#524000
0%
#526000
b1110 +
b1110 &
b1110 *
b1110 -
b1110 3
1%
#528000
0%
#530000
b1111 3
b1111 +
b1111 &
b1111 *
b1111 -
1%
#532000
0%
#534000
b0 +
1,
1"
b0 &
b0 *
b0 -
14
b0 3
1%
#536000
0%
#538000
b1 3
04
b1 +
0,
b1 &
b1 *
b1 -
0"
1%
#540000
0%
#542000
b10 +
b10 &
b10 *
b10 -
b10 3
1%
#544000
0%
#546000
b11 3
b11 +
b11 &
b11 *
b11 -
1%
#548000
0%
#550000
b100 +
b100 &
b100 *
b100 -
b100 3
1%
#552000
0%
#554000
b101 3
b101 +
b101 &
b101 *
b101 -
1%
#556000
0%
#558000
b110 +
b110 &
b110 *
b110 -
b110 3
1%
#560000
b1 #
b1 (
b1 /
b1 2
0%
#562000
b101 3
b101 +
b101 &
b101 *
b101 -
1%
#564000
0%
#566000
b100 +
b100 &
b100 *
b100 -
b100 3
1%
#568000
0%
#570000
b11 3
b11 +
b11 &
b11 *
b11 -
1%
#572000
0%
#574000
b10 +
b10 &
b10 *
b10 -
b10 3
1%
#576000
0%
#578000
b1 3
b1 +
b1 &
b1 *
b1 -
1%
#580000
0%
#582000
b0 +
b0 &
b0 *
b0 -
b0 3
1%
#584000
0%
#586000
14
b1111 3
b1111 +
1,
1"
b1111 &
b1111 *
b1111 -
1%
#588000
0%
#590000
b1110 +
0,
b1110 &
b1110 *
b1110 -
0"
b1110 3
04
1%
#592000
0%
#594000
b1101 3
b1101 +
b1101 &
b1101 *
b1101 -
1%
#596000
0%
#598000
b1100 +
b1100 &
b1100 *
b1100 -
b1100 3
1%
#600000
0%
#602000
b1011 3
b1011 +
b1011 &
b1011 *
b1011 -
1%
#604000
0%
#606000
b1010 +
b1010 &
b1010 *
b1010 -
b1010 3
1%
#608000
0%
#610000
b1001 3
b1001 +
b1001 &
b1001 *
b1001 -
1%
#612000
0%
#614000
b1000 +
b1000 &
b1000 *
b1000 -
b1000 3
1%
#616000
0%
#618000
b111 3
b111 +
b111 &
b111 *
b111 -
1%
#620000
0%
#622000
b110 +
b110 &
b110 *
b110 -
b110 3
1%
#624000
0%
#626000
b101 3
b101 +
b101 &
b101 *
b101 -
1%
#628000
0%
#630000
b100 +
b100 &
b100 *
b100 -
b100 3
1%
#632000
0%
#634000
b11 3
b11 +
b11 &
b11 *
b11 -
1%
#636000
0%
#638000
b10 +
b10 &
b10 *
b10 -
b10 3
1%
#640000
b10 #
b10 (
b10 /
b10 2
0%
#642000
14
b1111 3
b1111 +
1,
1"
b1111 &
b1111 *
b1111 -
1%
#644000
0%
#646000
b1100 +
0,
b1100 &
b1100 *
b1100 -
0"
b1100 3
04
1%
#648000
0%
#650000
b1001 3
b1001 +
b1001 &
b1001 *
b1001 -
1%
#652000
0%
#654000
b110 +
b110 &
b110 *
b110 -
b110 3
1%
#656000
0%
#658000
b11 3
b11 +
b11 &
b11 *
b11 -
1%
#660000
0%
#662000
b0 +
b0 &
b0 *
b0 -
b0 3
1%
#664000
0%
#666000
14
b1101 3
b1101 +
1,
1"
b1101 &
b1101 *
b1101 -
1%
#668000
0%
#670000
b1010 +
0,
b1010 &
b1010 *
b1010 -
0"
b1010 3
04
1%
#672000
0%
#674000
b111 3
b111 +
b111 &
b111 *
b111 -
1%
#676000
0%
#678000
b100 +
b100 &
b100 *
b100 -
b100 3
1%
#680000
0%
#682000
b1 3
b1 +
b1 &
b1 *
b1 -
1%
#684000
0%
#686000
b1110 +
1,
1"
b1110 &
b1110 *
b1110 -
14
b1110 3
1%
#688000
0%
#690000
b1011 3
04
b1011 +
0,
b1011 &
b1011 *
b1011 -
0"
1%
#692000
0%
#694000
b1000 +
b1000 &
b1000 *
b1000 -
b1000 3
1%
#696000
0%
#698000
b101 3
b101 +
b101 &
b101 *
b101 -
1%
#700000
0%
#702000
b10 +
b10 &
b10 *
b10 -
b10 3
1%
#704000
0%
#706000
14
b1111 3
b1111 +
1,
1"
b1111 &
b1111 *
b1111 -
1%
#708000
0%
#710000
b1100 +
0,
b1100 &
b1100 *
b1100 -
0"
b1100 3
04
1%
#712000
0%
#714000
b1001 3
b1001 +
b1001 &
b1001 *
b1001 -
1%
#716000
0%
#718000
b110 +
b110 &
b110 *
b110 -
b110 3
1%
#720000
b1111 '
b1111 )
b1111 .
b1111 1
0%
#722000
b11 3
b11 +
b11 &
b11 *
b11 -
1%
#724000
0%
#726000
b0 +
b0 &
b0 *
b0 -
b0 3
1%
#728000
0%
#730000
14
b1101 3
b1101 +
1,
1"
b1101 &
b1101 *
b1101 -
1%
#732000
0%
#734000
b1010 +
0,
b1010 &
b1010 *
b1010 -
0"
b1010 3
04
1%
#736000
0%
#738000
b111 3
b111 +
b111 &
b111 *
b111 -
1%
#740000
0%
#742000
b100 +
b100 &
b100 *
b100 -
b100 3
1%
#744000
0%
#746000
b1 3
b1 +
b1 &
b1 *
b1 -
1%
#748000
0%
#750000
b1110 +
1,
1"
b1110 &
b1110 *
b1110 -
14
b1110 3
1%
#752000
0%
#754000
b1011 3
04
b1011 +
0,
b1011 &
b1011 *
b1011 -
0"
1%
#756000
0%
#758000
b1000 +
b1000 &
b1000 *
b1000 -
b1000 3
1%
#760000
0%
#762000
b101 3
b101 +
b101 &
b101 *
b101 -
1%
#764000
0%
#766000
b10 +
b10 &
b10 *
b10 -
b10 3
1%
#768000
0%
#770000
14
b1111 3
b1111 +
1,
1"
b1111 &
b1111 *
b1111 -
1%
#772000
0%
#774000
b1100 +
0,
b1100 &
b1100 *
b1100 -
0"
b1100 3
04
1%
#776000
0%
#778000
b1001 3
b1001 +
b1001 &
b1001 *
b1001 -
1%
#780000
0%
#782000
b110 +
b110 &
b110 *
b110 -
b110 3
1%
#784000
0%
#786000
b11 3
b11 +
b11 &
b11 *
b11 -
1%
#788000
0%
#790000
b0 +
b0 &
b0 *
b0 -
b0 3
1%
#792000
0%
#794000
14
b1101 3
b1101 +
1,
1"
b1101 &
b1101 *
b1101 -
1%
#796000
0%
#798000
b1010 +
0,
b1010 &
b1010 *
b1010 -
0"
b1010 3
04
1%
#800000
0%
#802000
b111 3
b111 +
b111 &
b111 *
b111 -
1%
#804000
0%
#806000
b100 +
b100 &
b100 *
b100 -
b100 3
1%
#808000
0%
#810000
b1 3
b1 +
b1 &
b1 *
b1 -
1%
#812000
0%
#814000
b1110 +
1,
1"
b1110 &
b1110 *
b1110 -
14
b1110 3
1%
#816000
0%
#818000
b1011 3
04
b1011 +
0,
b1011 &
b1011 *
b1011 -
0"
1%
#820000
0%
#822000
b1000 +
b1000 &
b1000 *
b1000 -
b1000 3
1%
#824000
0%
#826000
b101 3
b101 +
b101 &
b101 *
b101 -
1%
#828000
0%
#830000
b10 +
b10 &
b10 *
b10 -
b10 3
1%
#832000
0%
#834000
14
b1111 3
b1111 +
1,
1"
b1111 &
b1111 *
b1111 -
1%
#836000
0%
#838000
b1100 +
0,
b1100 &
b1100 *
b1100 -
0"
b1100 3
04
1%
#840000
0%
#842000
b1001 3
b1001 +
b1001 &
b1001 *
b1001 -
1%
#844000
0%
#846000
b110 +
b110 &
b110 *
b110 -
b110 3
1%
#848000
0%
#850000
b11 3
b11 +
b11 &
b11 *
b11 -
1%
#852000
0%
#854000
b0 +
b0 &
b0 *
b0 -
b0 3
1%
#856000
0%
#858000
14
b1101 3
b1101 +
1,
1"
b1101 &
b1101 *
b1101 -
1%
#860000
0%
#862000
b1010 +
0,
b1010 &
b1010 *
b1010 -
0"
b1010 3
04
1%
#864000
0%
#866000
b111 3
b111 +
b111 &
b111 *
b111 -
1%
#868000
0%
#870000
b100 +
b100 &
b100 *
b100 -
b100 3
1%
#872000
0%
#874000
b1 3
b1 +
b1 &
b1 *
b1 -
1%
#876000
0%
#878000
b1110 +
1,
1"
b1110 &
b1110 *
b1110 -
14
b1110 3
1%
#880000
b11 #
b11 (
b11 /
b11 2
0%
#882000
b1111 3
b1111 +
b1111 &
b1111 *
b1111 -
1"
1%
#884000
0%
#886000
1"
1%
#888000
0%
#890000
1"
1%
#892000
1!
b0 #
b0 (
b0 /
b0 2
0%
#894000
b0 +
0,
0"
b0 &
b0 *
b0 -
04
b0 3
1%
#896000
0%
